[{"model": "admin.logentry", "pk": 1, "fields": {"action_time": "2021-12-01T21:45:23.052Z", "user": 1, "content_type": 13, "object_id": "1", "object_repr": "New Consult", "action_flag": 1, "change_message": "[{\"added\": {}}]"}}, {"model": "admin.logentry", "pk": 2, "fields": {"action_time": "2021-12-01T21:46:07.922Z", "user": 1, "content_type": 13, "object_id": "2", "object_repr": "Follow up Consulation", "action_flag": 1, "change_message": "[{\"added\": {}}]"}}, {"model": "admin.logentry", "pk": 3, "fields": {"action_time": "2021-12-01T21:46:51.797Z", "user": 1, "content_type": 13, "object_id": "3", "object_repr": "Help  my plants", "action_flag": 1, "change_message": "[{\"added\": {}}]"}}, {"model": "admin.logentry", "pk": 4, "fields": {"action_time": "2021-12-01T21:48:46.847Z", "user": 1, "content_type": 8, "object_id": "1", "object_repr": "lisa-hackett@hotmail.com", "action_flag": 1, "change_message": "[{\"added\": {}}]"}}, {"model": "admin.logentry", "pk": 5, "fields": {"action_time": "2021-12-01T21:49:39.298Z", "user": 1, "content_type": 7, "object_id": "1", "object_repr": "Help_My_Plants", "action_flag": 2, "change_message": "[{\"changed\": {\"fields\": [\"Domain name\", \"Display name\"]}}]"}}, {"model": "admin.logentry", "pk": 6, "fields": {"action_time": "2021-12-02T07:32:46.564Z", "user": 1, "content_type": 13, "object_id": "3", "object_repr": "Help  my plants", "action_flag": 2, "change_message": "[{\"changed\": {\"fields\": [\"Time slot\", \"Image\"]}}]"}}, {"model": "admin.logentry", "pk": 7, "fields": {"action_time": "2021-12-02T07:34:27.432Z", "user": 1, "content_type": 13, "object_id": "1", "object_repr": "New Consult", "action_flag": 2, "change_message": "[{\"changed\": {\"fields\": [\"Image\"]}}]"}}, {"model": "admin.logentry", "pk": 8, "fields": {"action_time": "2021-12-02T07:45:21.940Z", "user": 1, "content_type": 13, "object_id": "4", "object_repr": "test", "action_flag": 1, "change_message": "[{\"added\": {}}]"}}, {"model": "admin.logentry", "pk": 9, "fields": {"action_time": "2021-12-02T07:59:35.799Z", "user": 1, "content_type": 13, "object_id": "1", "object_repr": "New Consult", "action_flag": 2, "change_message": "[{\"changed\": {\"fields\": [\"Image\"]}}]"}}, {"model": "admin.logentry", "pk": 10, "fields": {"action_time": "2021-12-02T08:00:13.143Z", "user": 1, "content_type": 13, "object_id": "3", "object_repr": "Help  my plants", "action_flag": 2, "change_message": "[{\"changed\": {\"fields\": [\"Image\"]}}]"}}, {"model": "admin.logentry", "pk": 11, "fields": {"action_time": "2021-12-02T08:00:26.257Z", "user": 1, "content_type": 13, "object_id": "3", "object_repr": "Help  my plants", "action_flag": 2, "change_message": "[{\"changed\": {\"fields\": [\"Image\"]}}]"}}, {"model": "admin.logentry", "pk": 12, "fields": {"action_time": "2021-12-02T08:01:06.208Z", "user": 1, "content_type": 13, "object_id": "3", "object_repr": "Help  my plants", "action_flag": 2, "change_message": "[{\"changed\": {\"fields\": [\"Image\"]}}]"}}, {"model": "admin.logentry", "pk": 13, "fields": {"action_time": "2021-12-02T08:01:24.708Z", "user": 1, "content_type": 13, "object_id": "3", "object_repr": "Help  my plants", "action_flag": 2, "change_message": "[{\"changed\": {\"fields\": [\"Image\"]}}]"}}, {"model": "admin.logentry", "pk": 14, "fields": {"action_time": "2021-12-04T12:43:39.720Z", "user": 1, "content_type": 16, "object_id": "1", "object_repr": "Test Article", "action_flag": 1, "change_message": "[{\"added\": {}}]"}}, {"model": "admin.logentry", "pk": 15, "fields": {"action_time": "2021-12-05T15:40:07.804Z", "user": 1, "content_type": 8, "object_id": "2", "object_repr": "lisa.hackett@ucdconnect.ie", "action_flag": 2, "change_message": "[{\"changed\": {\"fields\": [\"Verified\"]}}]"}}, {"model": "admin.logentry", "pk": 16, "fields": {"action_time": "2021-12-05T16:52:35.769Z", "user": 1, "content_type": 13, "object_id": "5", "object_repr": "gfafda", "action_flag": 2, "change_message": "[{\"changed\": {\"fields\": [\"Image\"]}}]"}}, {"model": "admin.logentry", "pk": 17, "fields": {"action_time": "2021-12-05T16:52:52.750Z", "user": 1, "content_type": 13, "object_id": "5", "object_repr": "gfafda", "action_flag": 2, "change_message": "[{\"changed\": {\"fields\": [\"Image\"]}}]"}}, {"model": "admin.logentry", "pk": 18, "fields": {"action_time": "2021-12-05T16:53:35.941Z", "user": 1, "content_type": 13, "object_id": "5", "object_repr": "gfafda", "action_flag": 2, "change_message": "[{\"changed\": {\"fields\": [\"Image\"]}}]"}}, {"model": "admin.logentry", "pk": 19, "fields": {"action_time": "2021-12-05T16:53:46.170Z", "user": 1, "content_type": 13, "object_id": "5", "object_repr": "gfafda", "action_flag": 2, "change_message": "[{\"changed\": {\"fields\": [\"Image\"]}}]"}}, {"model": "admin.logentry", "pk": 20, "fields": {"action_time": "2021-12-05T16:54:49.929Z", "user": 1, "content_type": 13, "object_id": "4", "object_repr": "test", "action_flag": 2, "change_message": "[{\"changed\": {\"fields\": [\"Image\"]}}]"}}, {"model": "admin.logentry", "pk": 21, "fields": {"action_time": "2021-12-05T16:54:57.649Z", "user": 1, "content_type": 13, "object_id": "2", "object_repr": "Follow up Consulation", "action_flag": 2, "change_message": "[{\"changed\": {\"fields\": [\"Image\"]}}]"}}, {"model": "admin.logentry", "pk": 22, "fields": {"action_time": "2021-12-05T16:55:08.960Z", "user": 1, "content_type": 13, "object_id": "2", "object_repr": "Follow up Consulation", "action_flag": 2, "change_message": "[{\"changed\": {\"fields\": [\"Image\"]}}]"}}, {"model": "admin.logentry", "pk": 23, "fields": {"action_time": "2021-12-05T16:55:15.306Z", "user": 1, "content_type": 13, "object_id": "1", "object_repr": "New Consult", "action_flag": 2, "change_message": "[{\"changed\": {\"fields\": [\"Image\"]}}]"}}, {"model": "admin.logentry", "pk": 24, "fields": {"action_time": "2021-12-05T16:55:33.833Z", "user": 1, "content_type": 13, "object_id": "1", "object_repr": "New Consult", "action_flag": 2, "change_message": "[{\"changed\": {\"fields\": [\"Image\"]}}]"}}, {"model": "admin.logentry", "pk": 25, "fields": {"action_time": "2021-12-05T16:56:16.223Z", "user": 1, "content_type": 16, "object_id": "1", "object_repr": "Test Article", "action_flag": 2, "change_message": "[{\"changed\": {\"fields\": [\"Image\"]}}]"}}, {"model": "admin.logentry", "pk": 26, "fields": {"action_time": "2021-12-05T16:57:38.742Z", "user": 1, "content_type": 16, "object_id": "1", "object_repr": "Test Article", "action_flag": 2, "change_message": "[{\"changed\": {\"fields\": [\"Image\"]}}]"}}, {"model": "admin.logentry", "pk": 27, "fields": {"action_time": "2021-12-05T16:57:53.927Z", "user": 1, "content_type": 16, "object_id": "1", "object_repr": "Test Article", "action_flag": 2, "change_message": "[{\"changed\": {\"fields\": [\"Image\"]}}]"}}, {"model": "admin.logentry", "pk": 28, "fields": {"action_time": "2021-12-05T17:54:58.370Z", "user": 1, "content_type": 16, "object_id": "2", "object_repr": "Health Benefits of Plants", "action_flag": 1, "change_message": "[{\"added\": {}}]"}}, {"model": "admin.logentry", "pk": 29, "fields": {"action_time": "2021-12-05T17:56:32.622Z", "user": 1, "content_type": 16, "object_id": "2", "object_repr": "Health Benefits of Plants", "action_flag": 2, "change_message": "[{\"changed\": {\"fields\": [\"Image\"]}}]"}}, {"model": "admin.logentry", "pk": 30, "fields": {"action_time": "2021-12-05T19:52:12.647Z", "user": 1, "content_type": 16, "object_id": "2", "object_repr": "Health Benefits of Plants", "action_flag": 2, "change_message": "[{\"changed\": {\"fields\": [\"Image\"]}}]"}}, {"model": "admin.logentry", "pk": 31, "fields": {"action_time": "2021-12-05T19:52:46.564Z", "user": 1, "content_type": 16, "object_id": "2", "object_repr": "Health Benefits of Plants", "action_flag": 2, "change_message": "[{\"changed\": {\"fields\": [\"Image\"]}}]"}}, {"model": "admin.logentry", "pk": 32, "fields": {"action_time": "2021-12-05T20:17:39.843Z", "user": 1, "content_type": 13, "object_id": "5", "object_repr": "gfafda", "action_flag": 2, "change_message": "[{\"changed\": {\"fields\": [\"Image\"]}}]"}}, {"model": "admin.logentry", "pk": 33, "fields": {"action_time": "2021-12-05T20:18:08.491Z", "user": 1, "content_type": 13, "object_id": "2", "object_repr": "Follow up Consulation", "action_flag": 2, "change_message": "[{\"changed\": {\"fields\": [\"Image\"]}}]"}}, {"model": "admin.logentry", "pk": 34, "fields": {"action_time": "2021-12-05T20:18:14.758Z", "user": 1, "content_type": 13, "object_id": "1", "object_repr": "New Consult", "action_flag": 2, "change_message": "[{\"changed\": {\"fields\": [\"Image\"]}}]"}}, {"model": "admin.logentry", "pk": 35, "fields": {"action_time": "2021-12-05T20:23:24.234Z", "user": 1, "content_type": 13, "object_id": "3", "object_repr": "Help  my plants", "action_flag": 2, "change_message": "[{\"changed\": {\"fields\": [\"Image\"]}}]"}}, {"model": "admin.logentry", "pk": 36, "fields": {"action_time": "2021-12-05T21:18:01.528Z", "user": 1, "content_type": 13, "object_id": "5", "object_repr": "gfafda", "action_flag": 2, "change_message": "[{\"changed\": {\"fields\": [\"Image\"]}}]"}}, {"model": "admin.logentry", "pk": 37, "fields": {"action_time": "2021-12-05T21:18:20.479Z", "user": 1, "content_type": 13, "object_id": "4", "object_repr": "test", "action_flag": 2, "change_message": "[{\"changed\": {\"fields\": [\"Image\"]}}]"}}, {"model": "admin.logentry", "pk": 38, "fields": {"action_time": "2021-12-05T21:18:37.424Z", "user": 1, "content_type": 13, "object_id": "3", "object_repr": "Help  my plants", "action_flag": 2, "change_message": "[{\"changed\": {\"fields\": [\"Image\"]}}]"}}, {"model": "admin.logentry", "pk": 39, "fields": {"action_time": "2021-12-05T21:18:58.026Z", "user": 1, "content_type": 13, "object_id": "2", "object_repr": "Follow up Consulation", "action_flag": 2, "change_message": "[{\"changed\": {\"fields\": [\"Image\"]}}]"}}, {"model": "admin.logentry", "pk": 40, "fields": {"action_time": "2021-12-05T21:19:13.467Z", "user": 1, "content_type": 13, "object_id": "1", "object_repr": "New Consult", "action_flag": 2, "change_message": "[{\"changed\": {\"fields\": [\"Image\"]}}]"}}, {"model": "admin.logentry", "pk": 41, "fields": {"action_time": "2021-12-05T21:23:05.687Z", "user": 1, "content_type": 13, "object_id": "5", "object_repr": "gfafda", "action_flag": 2, "change_message": "[{\"changed\": {\"fields\": [\"Image\"]}}]"}}, {"model": "admin.logentry", "pk": 42, "fields": {"action_time": "2021-12-05T21:23:23.269Z", "user": 1, "content_type": 13, "object_id": "5", "object_repr": "gfafda", "action_flag": 2, "change_message": "[{\"changed\": {\"fields\": [\"Image\"]}}]"}}, {"model": "admin.logentry", "pk": 43, "fields": {"action_time": "2021-12-05T21:23:31.130Z", "user": 1, "content_type": 13, "object_id": "4", "object_repr": "test", "action_flag": 2, "change_message": "[{\"changed\": {\"fields\": [\"Image\"]}}]"}}, {"model": "admin.logentry", "pk": 44, "fields": {"action_time": "2021-12-05T21:23:48.793Z", "user": 1, "content_type": 13, "object_id": "4", "object_repr": "test", "action_flag": 2, "change_message": "[]"}}, {"model": "admin.logentry", "pk": 45, "fields": {"action_time": "2021-12-05T21:23:57.039Z", "user": 1, "content_type": 13, "object_id": "3", "object_repr": "Help  my plants", "action_flag": 2, "change_message": "[{\"changed\": {\"fields\": [\"Image\"]}}]"}}, {"model": "admin.logentry", "pk": 46, "fields": {"action_time": "2021-12-05T21:24:12.769Z", "user": 1, "content_type": 13, "object_id": "3", "object_repr": "Help  my plants", "action_flag": 2, "change_message": "[{\"changed\": {\"fields\": [\"Image\"]}}]"}}, {"model": "admin.logentry", "pk": 47, "fields": {"action_time": "2021-12-05T21:24:19.976Z", "user": 1, "content_type": 13, "object_id": "2", "object_repr": "Follow up Consulation", "action_flag": 2, "change_message": "[{\"changed\": {\"fields\": [\"Image\"]}}]"}}, {"model": "admin.logentry", "pk": 48, "fields": {"action_time": "2021-12-05T21:24:34.807Z", "user": 1, "content_type": 13, "object_id": "2", "object_repr": "Follow up Consulation", "action_flag": 2, "change_message": "[{\"changed\": {\"fields\": [\"Image\"]}}]"}}, {"model": "admin.logentry", "pk": 49, "fields": {"action_time": "2021-12-05T21:24:53.362Z", "user": 1, "content_type": 13, "object_id": "1", "object_repr": "New Consult", "action_flag": 2, "change_message": "[{\"changed\": {\"fields\": [\"Image\"]}}]"}}, {"model": "admin.logentry", "pk": 50, "fields": {"action_time": "2021-12-05T21:25:13.791Z", "user": 1, "content_type": 13, "object_id": "1", "object_repr": "New Consult", "action_flag": 2, "change_message": "[{\"changed\": {\"fields\": [\"Image\"]}}]"}}, {"model": "admin.logentry", "pk": 51, "fields": {"action_time": "2021-12-05T21:25:22.351Z", "user": 1, "content_type": 13, "object_id": "3", "object_repr": "Help  my plants", "action_flag": 2, "change_message": "[{\"changed\": {\"fields\": [\"Image\"]}}]"}}, {"model": "admin.logentry", "pk": 52, "fields": {"action_time": "2021-12-05T21:26:04.908Z", "user": 1, "content_type": 13, "object_id": "3", "object_repr": "Help  my plants", "action_flag": 2, "change_message": "[{\"changed\": {\"fields\": [\"Image\"]}}]"}}, {"model": "admin.logentry", "pk": 53, "fields": {"action_time": "2021-12-05T21:27:39.049Z", "user": 1, "content_type": 13, "object_id": "4", "object_repr": "test", "action_flag": 2, "change_message": "[{\"changed\": {\"fields\": [\"Image\"]}}]"}}, {"model": "admin.logentry", "pk": 54, "fields": {"action_time": "2021-12-06T07:26:15.540Z", "user": 1, "content_type": 13, "object_id": "4", "object_repr": "test", "action_flag": 2, "change_message": "[{\"changed\": {\"fields\": [\"Image\"]}}]"}}, {"model": "admin.logentry", "pk": 55, "fields": {"action_time": "2021-12-06T07:26:25.636Z", "user": 1, "content_type": 13, "object_id": "4", "object_repr": "test", "action_flag": 2, "change_message": "[{\"changed\": {\"fields\": [\"Image\"]}}]"}}, {"model": "admin.logentry", "pk": 56, "fields": {"action_time": "2021-12-09T16:37:58.150Z", "user": 1, "content_type": 14, "object_id": "39", "object_repr": "8F7CE575D4DC4DA6940E9E23972C7587", "action_flag": 3, "change_message": ""}}, {"model": "admin.logentry", "pk": 57, "fields": {"action_time": "2021-12-09T16:37:58.156Z", "user": 1, "content_type": 14, "object_id": "38", "object_repr": "D5231DA723804ED289899FEC75D674FC", "action_flag": 3, "change_message": ""}}, {"model": "admin.logentry", "pk": 58, "fields": {"action_time": "2021-12-09T16:37:58.159Z", "user": 1, "content_type": 14, "object_id": "37", "object_repr": "EACF2BB500AA42188FEB47EF02196836", "action_flag": 3, "change_message": ""}}, {"model": "admin.logentry", "pk": 59, "fields": {"action_time": "2021-12-09T16:37:58.163Z", "user": 1, "content_type": 14, "object_id": "36", "object_repr": "9D6A3E9BA5464B14A961122CC41FABA8", "action_flag": 3, "change_message": ""}}, {"model": "admin.logentry", "pk": 60, "fields": {"action_time": "2021-12-09T16:37:58.167Z", "user": 1, "content_type": 14, "object_id": "35", "object_repr": "4F58EDFDD19C4D3B95DA33F842B5FABF", "action_flag": 3, "change_message": ""}}, {"model": "admin.logentry", "pk": 61, "fields": {"action_time": "2021-12-09T16:37:58.170Z", "user": 1, "content_type": 14, "object_id": "34", "object_repr": "5BBA5B0F0C4F4A9699C8DE7B15D8105D", "action_flag": 3, "change_message": ""}}, {"model": "admin.logentry", "pk": 62, "fields": {"action_time": "2021-12-09T16:37:58.174Z", "user": 1, "content_type": 14, "object_id": "33", "object_repr": "37CD3AC50B734FB99125447818F4471C", "action_flag": 3, "change_message": ""}}, {"model": "admin.logentry", "pk": 63, "fields": {"action_time": "2021-12-09T16:37:58.178Z", "user": 1, "content_type": 14, "object_id": "32", "object_repr": "66D46EF237BB422BA64552F3D84C36AA", "action_flag": 3, "change_message": ""}}, {"model": "admin.logentry", "pk": 64, "fields": {"action_time": "2021-12-09T16:37:58.184Z", "user": 1, "content_type": 14, "object_id": "31", "object_repr": "BDC92B1FC84F4C2AA57675B351E61F58", "action_flag": 3, "change_message": ""}}, {"model": "admin.logentry", "pk": 65, "fields": {"action_time": "2021-12-09T16:37:58.190Z", "user": 1, "content_type": 14, "object_id": "30", "object_repr": "9B71939C329B413680D623964123D1F5", "action_flag": 3, "change_message": ""}}, {"model": "admin.logentry", "pk": 66, "fields": {"action_time": "2021-12-09T16:37:58.195Z", "user": 1, "content_type": 14, "object_id": "29", "object_repr": "32149B59720045AC96129C600719E1D8", "action_flag": 3, "change_message": ""}}, {"model": "admin.logentry", "pk": 67, "fields": {"action_time": "2021-12-09T16:37:58.199Z", "user": 1, "content_type": 14, "object_id": "28", "object_repr": "9A812AAD71514EAB9FF2B9E850719F42", "action_flag": 3, "change_message": ""}}, {"model": "admin.logentry", "pk": 68, "fields": {"action_time": "2021-12-09T16:37:58.203Z", "user": 1, "content_type": 14, "object_id": "27", "object_repr": "43C95AD5AFA742A68F47DF42C62CCC2B", "action_flag": 3, "change_message": ""}}, {"model": "admin.logentry", "pk": 69, "fields": {"action_time": "2021-12-09T16:37:58.207Z", "user": 1, "content_type": 14, "object_id": "26", "object_repr": "01E4373C7D4A44749522A6D3E7D49CC3", "action_flag": 3, "change_message": ""}}, {"model": "admin.logentry", "pk": 70, "fields": {"action_time": "2021-12-09T16:37:58.210Z", "user": 1, "content_type": 14, "object_id": "25", "object_repr": "4C6F066DFDE94101AA22E54006AF2867", "action_flag": 3, "change_message": ""}}, {"model": "admin.logentry", "pk": 71, "fields": {"action_time": "2021-12-09T16:37:58.215Z", "user": 1, "content_type": 14, "object_id": "24", "object_repr": "92B946E4CD5042BE9A0CC867C772E6EE", "action_flag": 3, "change_message": ""}}, {"model": "admin.logentry", "pk": 72, "fields": {"action_time": "2021-12-09T16:37:58.218Z", "user": 1, "content_type": 14, "object_id": "23", "object_repr": "0FD361A1F55C4C4F8AB375A1A55E2663", "action_flag": 3, "change_message": ""}}, {"model": "admin.logentry", "pk": 73, "fields": {"action_time": "2021-12-09T16:37:58.221Z", "user": 1, "content_type": 14, "object_id": "22", "object_repr": "39C82D05311A465A8A634392691592CB", "action_flag": 3, "change_message": ""}}, {"model": "admin.logentry", "pk": 74, "fields": {"action_time": "2021-12-09T16:37:58.224Z", "user": 1, "content_type": 14, "object_id": "21", "object_repr": "9F681C72627C4B468D80B6E8A1B87931", "action_flag": 3, "change_message": ""}}, {"model": "admin.logentry", "pk": 75, "fields": {"action_time": "2021-12-09T16:37:58.227Z", "user": 1, "content_type": 14, "object_id": "20", "object_repr": "0BE9106D0A0F415BBFF1A645572F3CB4", "action_flag": 3, "change_message": ""}}, {"model": "admin.logentry", "pk": 76, "fields": {"action_time": "2021-12-09T16:37:58.230Z", "user": 1, "content_type": 14, "object_id": "19", "object_repr": "EE74EDF9CA2A48809D42638C2545317B", "action_flag": 3, "change_message": ""}}, {"model": "admin.logentry", "pk": 77, "fields": {"action_time": "2021-12-09T16:37:58.234Z", "user": 1, "content_type": 14, "object_id": "18", "object_repr": "2B65C713E59E4037A63B04B111A9B2D3", "action_flag": 3, "change_message": ""}}, {"model": "admin.logentry", "pk": 78, "fields": {"action_time": "2021-12-09T16:37:58.237Z", "user": 1, "content_type": 14, "object_id": "17", "object_repr": "4E177D2F2070470FBEF868443BDC5A6B", "action_flag": 3, "change_message": ""}}, {"model": "admin.logentry", "pk": 79, "fields": {"action_time": "2021-12-09T16:37:58.240Z", "user": 1, "content_type": 14, "object_id": "16", "object_repr": "F74BFDC4B5B44C42A45E59ACCCA74679", "action_flag": 3, "change_message": ""}}, {"model": "admin.logentry", "pk": 80, "fields": {"action_time": "2021-12-09T16:37:58.244Z", "user": 1, "content_type": 14, "object_id": "15", "object_repr": "1C620EF8EE4E4B02AEE657FE4C5C0BAE", "action_flag": 3, "change_message": ""}}, {"model": "admin.logentry", "pk": 81, "fields": {"action_time": "2021-12-09T16:37:58.248Z", "user": 1, "content_type": 14, "object_id": "14", "object_repr": "EB36E1E7E7374B549E5C6CA7432E3224", "action_flag": 3, "change_message": ""}}, {"model": "admin.logentry", "pk": 82, "fields": {"action_time": "2021-12-09T16:37:58.252Z", "user": 1, "content_type": 14, "object_id": "13", "object_repr": "777C970C4EA24DD8A11D7186BD841061", "action_flag": 3, "change_message": ""}}, {"model": "admin.logentry", "pk": 83, "fields": {"action_time": "2021-12-09T16:37:58.256Z", "user": 1, "content_type": 14, "object_id": "12", "object_repr": "64C5814A196A42C6967C504BFCA76673", "action_flag": 3, "change_message": ""}}, {"model": "admin.logentry", "pk": 84, "fields": {"action_time": "2021-12-09T16:37:58.260Z", "user": 1, "content_type": 14, "object_id": "11", "object_repr": "66A6117D41D9471C863B61F5AC4BF793", "action_flag": 3, "change_message": ""}}, {"model": "admin.logentry", "pk": 85, "fields": {"action_time": "2021-12-09T16:37:58.264Z", "user": 1, "content_type": 14, "object_id": "10", "object_repr": "765256C3BF374255A407A72ACC03B742", "action_flag": 3, "change_message": ""}}, {"model": "admin.logentry", "pk": 86, "fields": {"action_time": "2021-12-09T16:37:58.268Z", "user": 1, "content_type": 14, "object_id": "9", "object_repr": "32F76B1652A849878BE24B79868F2514", "action_flag": 3, "change_message": ""}}, {"model": "admin.logentry", "pk": 87, "fields": {"action_time": "2021-12-09T16:37:58.271Z", "user": 1, "content_type": 14, "object_id": "8", "object_repr": "602FEE055D1543FCAC3DEBC4DC9A44C3", "action_flag": 3, "change_message": ""}}, {"model": "admin.logentry", "pk": 88, "fields": {"action_time": "2021-12-09T16:37:58.276Z", "user": 1, "content_type": 14, "object_id": "7", "object_repr": "9FE9F57EC1A74E2289DBF52EC8DD3342", "action_flag": 3, "change_message": ""}}, {"model": "admin.logentry", "pk": 89, "fields": {"action_time": "2021-12-09T16:37:58.280Z", "user": 1, "content_type": 14, "object_id": "6", "object_repr": "CC87E2966EA24C41B32CCFA645FEE1C3", "action_flag": 3, "change_message": ""}}, {"model": "admin.logentry", "pk": 90, "fields": {"action_time": "2021-12-09T16:37:58.284Z", "user": 1, "content_type": 14, "object_id": "5", "object_repr": "9BCD142DB5B841669663BB5ACCAA9139", "action_flag": 3, "change_message": ""}}, {"model": "admin.logentry", "pk": 91, "fields": {"action_time": "2021-12-09T16:37:58.288Z", "user": 1, "content_type": 14, "object_id": "4", "object_repr": "7A324D1E03B74AAC8980A62D380E82A7", "action_flag": 3, "change_message": ""}}, {"model": "admin.logentry", "pk": 92, "fields": {"action_time": "2021-12-09T16:37:58.292Z", "user": 1, "content_type": 14, "object_id": "3", "object_repr": "A6C68921C9C84B6C950849C5B6DBF6D5", "action_flag": 3, "change_message": ""}}, {"model": "admin.logentry", "pk": 93, "fields": {"action_time": "2021-12-09T16:37:58.296Z", "user": 1, "content_type": 14, "object_id": "2", "object_repr": "3E98F77662E04CC682A8335BA03F33ED", "action_flag": 3, "change_message": ""}}, {"model": "admin.logentry", "pk": 94, "fields": {"action_time": "2021-12-09T16:37:58.299Z", "user": 1, "content_type": 14, "object_id": "1", "object_repr": "3016A2ACBE714258A87B1C4D0FE2FE3D", "action_flag": 3, "change_message": ""}}, {"model": "admin.logentry", "pk": 95, "fields": {"action_time": "2021-12-11T19:12:48.150Z", "user": 1, "content_type": 14, "object_id": "133", "object_repr": "35D13F9F17054F28A5F9CB700C765C96", "action_flag": 1, "change_message": "[{\"added\": {}}, {\"added\": {\"name\": \"order item\", \"object\": \"Order total 55.00 for order number 35D13F9F17054F28A5F9CB700C765C96\"}}]"}}, {"model": "admin.logentry", "pk": 96, "fields": {"action_time": "2021-12-11T19:48:34.224Z", "user": 1, "content_type": 14, "object_id": "97", "object_repr": "7CD0B3A3799E42E3B00D30C9B7E7A0AF", "action_flag": 2, "change_message": "[]"}}, {"model": "admin.logentry", "pk": 97, "fields": {"action_time": "2021-12-11T19:49:12.102Z", "user": 1, "content_type": 14, "object_id": "136", "object_repr": "A96861E658E44FC6B307B79F683A73B1", "action_flag": 1, "change_message": "[{\"added\": {}}, {\"added\": {\"name\": \"order item\", \"object\": \"Order total 45.00 for order number A96861E658E44FC6B307B79F683A73B1\"}}, {\"added\": {\"name\": \"order item\", \"object\": \"Order total 55.00 for order number A96861E658E44FC6B307B79F683A73B1\"}}]"}}, {"model": "admin.logentry", "pk": 98, "fields": {"action_time": "2021-12-13T07:34:51.354Z", "user": 5, "content_type": 8, "object_id": "1", "object_repr": "lisa-hackett@hotmail.com", "action_flag": 3, "change_message": ""}}, {"model": "admin.logentry", "pk": 99, "fields": {"action_time": "2021-12-13T07:35:10.030Z", "user": 5, "content_type": 8, "object_id": "3", "object_repr": "lhackett79@gmail.com", "action_flag": 2, "change_message": "[{\"changed\": {\"fields\": [\"Verified\"]}}]"}}, {"model": "admin.logentry", "pk": 100, "fields": {"action_time": "2021-12-13T07:37:32.822Z", "user": 5, "content_type": 4, "object_id": "4", "object_repr": "NewTester", "action_flag": 3, "change_message": ""}}, {"model": "admin.logentry", "pk": 101, "fields": {"action_time": "2021-12-13T07:42:37.265Z", "user": 5, "content_type": 8, "object_id": "4", "object_repr": "lisa-hackett@hotmail.com", "action_flag": 2, "change_message": "[{\"changed\": {\"fields\": [\"Verified\", \"Primary\"]}}]"}}, {"model": "admin.logentry", "pk": 102, "fields": {"action_time": "2021-12-13T21:10:09.741Z", "user": 5, "content_type": 14, "object_id": "204", "object_repr": "C54E01FF3E0C436F985C2CB1A0D236B3", "action_flag": 2, "change_message": "[{\"changed\": {\"fields\": [\"Time slot\"]}}]"}}, {"model": "admin.logentry", "pk": 103, "fields": {"action_time": "2021-12-13T21:21:56.336Z", "user": 5, "content_type": 14, "object_id": "206", "object_repr": "CBFADD3E8C3E41B380434A7EB362EFE5", "action_flag": 2, "change_message": "[{\"changed\": {\"name\": \"order item\", \"object\": \"Order total 60.00 for order number CBFADD3E8C3E41B380434A7EB362EFE5\", \"fields\": [\"Date picked\"]}}, {\"changed\": {\"name\": \"order item\", \"object\": \"Order total 55.00 for order number CBFADD3E8C3E41B380434A7EB362EFE5\", \"fields\": [\"Date picked\"]}}, {\"changed\": {\"name\": \"order item\", \"object\": \"Order total 35.00 for order number CBFADD3E8C3E41B380434A7EB362EFE5\", \"fields\": [\"Date picked\"]}}]"}}, {"model": "admin.logentry", "pk": 104, "fields": {"action_time": "2021-12-14T00:02:24.701Z", "user": 5, "content_type": 13, "object_id": "7", "object_repr": "Health Benefits of Indoor Plants", "action_flag": 2, "change_message": "[{\"changed\": {\"fields\": [\"Image\"]}}]"}}, {"model": "admin.logentry", "pk": 105, "fields": {"action_time": "2021-12-14T16:57:45.095Z", "user": 5, "content_type": 8, "object_id": "6", "object_repr": "test@test.com", "action_flag": 1, "change_message": "[{\"added\": {}}]"}}, {"model": "admin.logentry", "pk": 106, "fields": {"action_time": "2021-12-14T18:22:32.896Z", "user": 5, "content_type": 14, "object_id": "203", "object_repr": "061A83470146479A9446D46BA814BD0F", "action_flag": 3, "change_message": ""}}, {"model": "admin.logentry", "pk": 107, "fields": {"action_time": "2021-12-14T18:22:32.901Z", "user": 5, "content_type": 14, "object_id": "202", "object_repr": "DF50F9CA907641BFA76FBD38E1E70C70", "action_flag": 3, "change_message": ""}}, {"model": "admin.logentry", "pk": 108, "fields": {"action_time": "2021-12-14T18:22:32.904Z", "user": 5, "content_type": 14, "object_id": "201", "object_repr": "3737684783C746DFAAAB71987347DE9C", "action_flag": 3, "change_message": ""}}, {"model": "admin.logentry", "pk": 109, "fields": {"action_time": "2021-12-14T18:22:32.908Z", "user": 5, "content_type": 14, "object_id": "200", "object_repr": "CCFE15F916B54D13A4606C1FAA6BF301", "action_flag": 3, "change_message": ""}}, {"model": "admin.logentry", "pk": 110, "fields": {"action_time": "2021-12-14T18:22:32.911Z", "user": 5, "content_type": 14, "object_id": "199", "object_repr": "371CBCD17772463F91415EB27A95EFBA", "action_flag": 3, "change_message": ""}}, {"model": "admin.logentry", "pk": 111, "fields": {"action_time": "2021-12-14T18:22:32.914Z", "user": 5, "content_type": 14, "object_id": "198", "object_repr": "9F595D3001C24B9B8BCE712BECD5F3CB", "action_flag": 3, "change_message": ""}}, {"model": "admin.logentry", "pk": 112, "fields": {"action_time": "2021-12-14T18:22:32.918Z", "user": 5, "content_type": 14, "object_id": "197", "object_repr": "1346FD16C70E49F9BB7D28C583B48184", "action_flag": 3, "change_message": ""}}, {"model": "admin.logentry", "pk": 113, "fields": {"action_time": "2021-12-14T18:22:32.922Z", "user": 5, "content_type": 14, "object_id": "196", "object_repr": "556D2B3825CF4E1FAAB6957E2319915B", "action_flag": 3, "change_message": ""}}, {"model": "admin.logentry", "pk": 114, "fields": {"action_time": "2021-12-14T18:22:32.926Z", "user": 5, "content_type": 14, "object_id": "195", "object_repr": "2A75DD5045464643BCB824D3EA3440D3", "action_flag": 3, "change_message": ""}}, {"model": "admin.logentry", "pk": 115, "fields": {"action_time": "2021-12-14T18:22:32.929Z", "user": 5, "content_type": 14, "object_id": "194", "object_repr": "6F532724CEFB40AFA5D859AC44E25A1C", "action_flag": 3, "change_message": ""}}, {"model": "admin.logentry", "pk": 116, "fields": {"action_time": "2021-12-14T18:22:32.933Z", "user": 5, "content_type": 14, "object_id": "193", "object_repr": "D8DB36C737E549FCB5F8BC72ED5B40DB", "action_flag": 3, "change_message": ""}}, {"model": "admin.logentry", "pk": 117, "fields": {"action_time": "2021-12-14T18:22:32.936Z", "user": 5, "content_type": 14, "object_id": "192", "object_repr": "03B34BD4CBC14BB6921FF3F6D6EC028A", "action_flag": 3, "change_message": ""}}, {"model": "admin.logentry", "pk": 118, "fields": {"action_time": "2021-12-14T18:22:32.940Z", "user": 5, "content_type": 14, "object_id": "191", "object_repr": "21A7A8CF1D9F42F5AA14F2FF948464AA", "action_flag": 3, "change_message": ""}}, {"model": "admin.logentry", "pk": 119, "fields": {"action_time": "2021-12-14T18:22:32.943Z", "user": 5, "content_type": 14, "object_id": "190", "object_repr": "08223CF80B624A35AF26DC2C4C1CDDE7", "action_flag": 3, "change_message": ""}}, {"model": "admin.logentry", "pk": 120, "fields": {"action_time": "2021-12-14T18:22:32.947Z", "user": 5, "content_type": 14, "object_id": "189", "object_repr": "4C698861765F42DF98A29CF0F003F9F4", "action_flag": 3, "change_message": ""}}, {"model": "admin.logentry", "pk": 121, "fields": {"action_time": "2021-12-14T18:22:32.950Z", "user": 5, "content_type": 14, "object_id": "188", "object_repr": "63D3F0612FA0433E86B740AA65D85C79", "action_flag": 3, "change_message": ""}}, {"model": "admin.logentry", "pk": 122, "fields": {"action_time": "2021-12-14T18:22:32.954Z", "user": 5, "content_type": 14, "object_id": "187", "object_repr": "DCFEEBED4D6B4731BC8CC9B744346EF1", "action_flag": 3, "change_message": ""}}, {"model": "admin.logentry", "pk": 123, "fields": {"action_time": "2021-12-14T18:22:32.958Z", "user": 5, "content_type": 14, "object_id": "186", "object_repr": "E1D76C3F4ACA4CC8B6D28008B45C5FF7", "action_flag": 3, "change_message": ""}}, {"model": "admin.logentry", "pk": 124, "fields": {"action_time": "2021-12-14T18:22:32.962Z", "user": 5, "content_type": 14, "object_id": "185", "object_repr": "387382B03C5D4B668EDCD3239D906678", "action_flag": 3, "change_message": ""}}, {"model": "admin.logentry", "pk": 125, "fields": {"action_time": "2021-12-14T18:22:32.965Z", "user": 5, "content_type": 14, "object_id": "184", "object_repr": "C5F0C397714043269265C941F4D252A4", "action_flag": 3, "change_message": ""}}, {"model": "admin.logentry", "pk": 126, "fields": {"action_time": "2021-12-14T18:22:32.969Z", "user": 5, "content_type": 14, "object_id": "183", "object_repr": "87BBFA6E5D824A6885E7D12EFEAAC9CF", "action_flag": 3, "change_message": ""}}, {"model": "admin.logentry", "pk": 127, "fields": {"action_time": "2021-12-14T18:22:32.973Z", "user": 5, "content_type": 14, "object_id": "182", "object_repr": "D14E3F1D09D144B79D2B2EFEA0F0420B", "action_flag": 3, "change_message": ""}}, {"model": "admin.logentry", "pk": 128, "fields": {"action_time": "2021-12-14T18:22:32.977Z", "user": 5, "content_type": 14, "object_id": "181", "object_repr": "7BEDDC7D718A4540963A7189E028D5EA", "action_flag": 3, "change_message": ""}}, {"model": "admin.logentry", "pk": 129, "fields": {"action_time": "2021-12-14T18:22:32.981Z", "user": 5, "content_type": 14, "object_id": "180", "object_repr": "875D808A95CE4721BF3D05EFEF6457E1", "action_flag": 3, "change_message": ""}}, {"model": "admin.logentry", "pk": 130, "fields": {"action_time": "2021-12-14T18:22:32.985Z", "user": 5, "content_type": 14, "object_id": "179", "object_repr": "D44F2679779242A5B442C48DED309EC2", "action_flag": 3, "change_message": ""}}, {"model": "admin.logentry", "pk": 131, "fields": {"action_time": "2021-12-14T18:22:32.988Z", "user": 5, "content_type": 14, "object_id": "178", "object_repr": "3CF3A838779A45108F2864882122EC7A", "action_flag": 3, "change_message": ""}}, {"model": "admin.logentry", "pk": 132, "fields": {"action_time": "2021-12-14T18:22:32.992Z", "user": 5, "content_type": 14, "object_id": "177", "object_repr": "AC066DE9E59A4414A3BC4D27E1E46DC7", "action_flag": 3, "change_message": ""}}, {"model": "admin.logentry", "pk": 133, "fields": {"action_time": "2021-12-14T18:22:32.996Z", "user": 5, "content_type": 14, "object_id": "176", "object_repr": "1D3642FB05104A3CBE20176D03242E9B", "action_flag": 3, "change_message": ""}}, {"model": "admin.logentry", "pk": 134, "fields": {"action_time": "2021-12-14T18:22:32.999Z", "user": 5, "content_type": 14, "object_id": "175", "object_repr": "75135FAC4215495687D4A038398901CF", "action_flag": 3, "change_message": ""}}, {"model": "admin.logentry", "pk": 135, "fields": {"action_time": "2021-12-14T18:22:33.003Z", "user": 5, "content_type": 14, "object_id": "174", "object_repr": "30C8BAF60F3748B38E5632805D66C27E", "action_flag": 3, "change_message": ""}}, {"model": "admin.logentry", "pk": 136, "fields": {"action_time": "2021-12-14T18:22:33.007Z", "user": 5, "content_type": 14, "object_id": "173", "object_repr": "3F8093559FFB44209CF9A302415F382D", "action_flag": 3, "change_message": ""}}, {"model": "admin.logentry", "pk": 137, "fields": {"action_time": "2021-12-14T18:22:33.010Z", "user": 5, "content_type": 14, "object_id": "172", "object_repr": "CC614094923E4434AC63D4A007371A9C", "action_flag": 3, "change_message": ""}}, {"model": "admin.logentry", "pk": 138, "fields": {"action_time": "2021-12-14T18:22:33.014Z", "user": 5, "content_type": 14, "object_id": "171", "object_repr": "1A3D864B095E455EB81BBF279476E6F7", "action_flag": 3, "change_message": ""}}, {"model": "admin.logentry", "pk": 139, "fields": {"action_time": "2021-12-14T18:22:33.017Z", "user": 5, "content_type": 14, "object_id": "170", "object_repr": "8C42B707EF9E4BB983FAA7BAA89875A8", "action_flag": 3, "change_message": ""}}, {"model": "admin.logentry", "pk": 140, "fields": {"action_time": "2021-12-14T18:22:33.021Z", "user": 5, "content_type": 14, "object_id": "169", "object_repr": "6DCB8D8102EE427A9F5A2C33B2A08B23", "action_flag": 3, "change_message": ""}}, {"model": "admin.logentry", "pk": 141, "fields": {"action_time": "2021-12-14T18:22:33.024Z", "user": 5, "content_type": 14, "object_id": "168", "object_repr": "2399C9A6BB694FCD803FB9BE845A7B1F", "action_flag": 3, "change_message": ""}}, {"model": "admin.logentry", "pk": 142, "fields": {"action_time": "2021-12-14T18:22:33.028Z", "user": 5, "content_type": 14, "object_id": "166", "object_repr": "79494A1F7A42425FA59DAC31D9FDC703", "action_flag": 3, "change_message": ""}}, {"model": "admin.logentry", "pk": 143, "fields": {"action_time": "2021-12-14T18:22:33.031Z", "user": 5, "content_type": 14, "object_id": "165", "object_repr": "B32556E2D3F94853B329A37A9FFADB16", "action_flag": 3, "change_message": ""}}, {"model": "admin.logentry", "pk": 144, "fields": {"action_time": "2021-12-14T18:22:33.034Z", "user": 5, "content_type": 14, "object_id": "164", "object_repr": "1EBB5211F5F749AC89FE6F68532C39EE", "action_flag": 3, "change_message": ""}}, {"model": "admin.logentry", "pk": 145, "fields": {"action_time": "2021-12-14T18:22:33.037Z", "user": 5, "content_type": 14, "object_id": "163", "object_repr": "8AE8167532E34E5C8525504EB3101D0B", "action_flag": 3, "change_message": ""}}, {"model": "admin.logentry", "pk": 146, "fields": {"action_time": "2021-12-14T18:22:33.040Z", "user": 5, "content_type": 14, "object_id": "162", "object_repr": "D1F4C1E8F5024952882BBCC14682FEC1", "action_flag": 3, "change_message": ""}}, {"model": "admin.logentry", "pk": 147, "fields": {"action_time": "2021-12-14T18:22:33.044Z", "user": 5, "content_type": 14, "object_id": "161", "object_repr": "0053E652B59A4DF0AC79B6E705D3F908", "action_flag": 3, "change_message": ""}}, {"model": "admin.logentry", "pk": 148, "fields": {"action_time": "2021-12-14T18:22:33.047Z", "user": 5, "content_type": 14, "object_id": "160", "object_repr": "89778BC427ED4A1A891CD1F12AE9A762", "action_flag": 3, "change_message": ""}}, {"model": "admin.logentry", "pk": 149, "fields": {"action_time": "2021-12-14T18:22:33.051Z", "user": 5, "content_type": 14, "object_id": "159", "object_repr": "AB07EF52AA824D38B7891BEF385EA912", "action_flag": 3, "change_message": ""}}, {"model": "admin.logentry", "pk": 150, "fields": {"action_time": "2021-12-14T18:22:33.054Z", "user": 5, "content_type": 14, "object_id": "158", "object_repr": "A863E6F9A09448C4A3CF6F1A4D9B292E", "action_flag": 3, "change_message": ""}}, {"model": "admin.logentry", "pk": 151, "fields": {"action_time": "2021-12-14T18:22:33.058Z", "user": 5, "content_type": 14, "object_id": "157", "object_repr": "4CBDE10EA1994D4BAD0A8FBD448A937C", "action_flag": 3, "change_message": ""}}, {"model": "admin.logentry", "pk": 152, "fields": {"action_time": "2021-12-14T18:22:33.062Z", "user": 5, "content_type": 14, "object_id": "156", "object_repr": "9C04E62C75764541856C9ECD3E259FF8", "action_flag": 3, "change_message": ""}}, {"model": "admin.logentry", "pk": 153, "fields": {"action_time": "2021-12-14T18:22:33.065Z", "user": 5, "content_type": 14, "object_id": "155", "object_repr": "F72761F2A7AA409CB7E90BC859A6ED0B", "action_flag": 3, "change_message": ""}}, {"model": "admin.logentry", "pk": 154, "fields": {"action_time": "2021-12-14T18:22:33.068Z", "user": 5, "content_type": 14, "object_id": "153", "object_repr": "3F67E00C905C421BB43D419EDCDB55AE", "action_flag": 3, "change_message": ""}}, {"model": "admin.logentry", "pk": 155, "fields": {"action_time": "2021-12-14T18:22:33.071Z", "user": 5, "content_type": 14, "object_id": "152", "object_repr": "39890DBE07A747A39DCB45F5FBD9A9A7", "action_flag": 3, "change_message": ""}}, {"model": "admin.logentry", "pk": 156, "fields": {"action_time": "2021-12-14T18:22:33.075Z", "user": 5, "content_type": 14, "object_id": "151", "object_repr": "317C2FDE032441C7933854B88FFBCC9C", "action_flag": 3, "change_message": ""}}, {"model": "admin.logentry", "pk": 157, "fields": {"action_time": "2021-12-14T18:22:33.078Z", "user": 5, "content_type": 14, "object_id": "150", "object_repr": "0863FF739E564A2797982E81571FBA33", "action_flag": 3, "change_message": ""}}, {"model": "admin.logentry", "pk": 158, "fields": {"action_time": "2021-12-14T18:22:33.082Z", "user": 5, "content_type": 14, "object_id": "149", "object_repr": "2BD032C1EC4D466CB51915BCF35AB8B8", "action_flag": 3, "change_message": ""}}, {"model": "admin.logentry", "pk": 159, "fields": {"action_time": "2021-12-14T18:22:33.085Z", "user": 5, "content_type": 14, "object_id": "148", "object_repr": "F2E933BDB18B43F6BB5B61FC6D3BA368", "action_flag": 3, "change_message": ""}}, {"model": "admin.logentry", "pk": 160, "fields": {"action_time": "2021-12-14T18:22:33.088Z", "user": 5, "content_type": 14, "object_id": "147", "object_repr": "E2366A687DE049ACBD58D8E407BD1751", "action_flag": 3, "change_message": ""}}, {"model": "admin.logentry", "pk": 161, "fields": {"action_time": "2021-12-14T18:22:33.091Z", "user": 5, "content_type": 14, "object_id": "146", "object_repr": "AD22C260F63D4B8DA96BC619F34CCF06", "action_flag": 3, "change_message": ""}}, {"model": "admin.logentry", "pk": 162, "fields": {"action_time": "2021-12-14T18:22:33.094Z", "user": 5, "content_type": 14, "object_id": "145", "object_repr": "038EC2C115434672B95F98CEC464F0B9", "action_flag": 3, "change_message": ""}}, {"model": "admin.logentry", "pk": 163, "fields": {"action_time": "2021-12-14T18:22:33.098Z", "user": 5, "content_type": 14, "object_id": "144", "object_repr": "3E3F150686534E98A0765F5CFB41DFDD", "action_flag": 3, "change_message": ""}}, {"model": "admin.logentry", "pk": 164, "fields": {"action_time": "2021-12-14T18:22:33.101Z", "user": 5, "content_type": 14, "object_id": "143", "object_repr": "148F1A333D7648389C64E7B065FFAD22", "action_flag": 3, "change_message": ""}}, {"model": "admin.logentry", "pk": 165, "fields": {"action_time": "2021-12-14T18:22:33.104Z", "user": 5, "content_type": 14, "object_id": "142", "object_repr": "DD30B543ED604A67926EB4B69C8F1890", "action_flag": 3, "change_message": ""}}, {"model": "admin.logentry", "pk": 166, "fields": {"action_time": "2021-12-14T18:22:33.108Z", "user": 5, "content_type": 14, "object_id": "141", "object_repr": "032F9EE4622B49F5A7CF2C514B5981C3", "action_flag": 3, "change_message": ""}}, {"model": "admin.logentry", "pk": 167, "fields": {"action_time": "2021-12-14T18:22:33.111Z", "user": 5, "content_type": 14, "object_id": "140", "object_repr": "C691E25A94AD42809808454B468DA1E0", "action_flag": 3, "change_message": ""}}, {"model": "admin.logentry", "pk": 168, "fields": {"action_time": "2021-12-14T18:22:33.115Z", "user": 5, "content_type": 14, "object_id": "139", "object_repr": "740198EEE812429B867303C3EEB29995", "action_flag": 3, "change_message": ""}}, {"model": "admin.logentry", "pk": 169, "fields": {"action_time": "2021-12-14T18:22:33.118Z", "user": 5, "content_type": 14, "object_id": "138", "object_repr": "83D1C72FD00046CCBFE790D91429AE83", "action_flag": 3, "change_message": ""}}, {"model": "admin.logentry", "pk": 170, "fields": {"action_time": "2021-12-14T18:22:33.122Z", "user": 5, "content_type": 14, "object_id": "137", "object_repr": "8D8D229C0FAD40C9B687630B9D1B79B2", "action_flag": 3, "change_message": ""}}, {"model": "admin.logentry", "pk": 171, "fields": {"action_time": "2021-12-14T18:22:33.125Z", "user": 5, "content_type": 14, "object_id": "136", "object_repr": "A96861E658E44FC6B307B79F683A73B1", "action_flag": 3, "change_message": ""}}, {"model": "admin.logentry", "pk": 172, "fields": {"action_time": "2021-12-14T18:22:33.128Z", "user": 5, "content_type": 14, "object_id": "135", "object_repr": "1166AF1295DB49AC88527DF6529F27A6", "action_flag": 3, "change_message": ""}}, {"model": "admin.logentry", "pk": 173, "fields": {"action_time": "2021-12-14T18:22:33.131Z", "user": 5, "content_type": 14, "object_id": "134", "object_repr": "02F6444705974DB4AC5BB3C3CDA2A38B", "action_flag": 3, "change_message": ""}}, {"model": "admin.logentry", "pk": 174, "fields": {"action_time": "2021-12-14T18:22:33.135Z", "user": 5, "content_type": 14, "object_id": "133", "object_repr": "35D13F9F17054F28A5F9CB700C765C96", "action_flag": 3, "change_message": ""}}, {"model": "admin.logentry", "pk": 175, "fields": {"action_time": "2021-12-14T18:22:33.138Z", "user": 5, "content_type": 14, "object_id": "132", "object_repr": "DA5A0CCE757044F394A759B9CA27CF9A", "action_flag": 3, "change_message": ""}}, {"model": "admin.logentry", "pk": 176, "fields": {"action_time": "2021-12-14T18:22:33.142Z", "user": 5, "content_type": 14, "object_id": "131", "object_repr": "AED2E3A24462497BBC936E2E6F3BE91B", "action_flag": 3, "change_message": ""}}, {"model": "admin.logentry", "pk": 177, "fields": {"action_time": "2021-12-14T18:22:33.145Z", "user": 5, "content_type": 14, "object_id": "130", "object_repr": "41A3BF149F92407A8E17E3D6889FE0DC", "action_flag": 3, "change_message": ""}}, {"model": "admin.logentry", "pk": 178, "fields": {"action_time": "2021-12-14T18:22:33.149Z", "user": 5, "content_type": 14, "object_id": "129", "object_repr": "34F5D167378E4E08B67C210CD0C83AC5", "action_flag": 3, "change_message": ""}}, {"model": "admin.logentry", "pk": 179, "fields": {"action_time": "2021-12-14T18:22:33.152Z", "user": 5, "content_type": 14, "object_id": "128", "object_repr": "3279E85E0BCD40B49DEA7E4DA2827B39", "action_flag": 3, "change_message": ""}}, {"model": "admin.logentry", "pk": 180, "fields": {"action_time": "2021-12-14T18:22:33.162Z", "user": 5, "content_type": 14, "object_id": "127", "object_repr": "01CF62A2C73048199D42522DF751932D", "action_flag": 3, "change_message": ""}}, {"model": "admin.logentry", "pk": 181, "fields": {"action_time": "2021-12-14T18:22:33.166Z", "user": 5, "content_type": 14, "object_id": "126", "object_repr": "1FBA186D3AFA41BAAB4C4033D80CC54F", "action_flag": 3, "change_message": ""}}, {"model": "admin.logentry", "pk": 182, "fields": {"action_time": "2021-12-14T18:22:33.170Z", "user": 5, "content_type": 14, "object_id": "125", "object_repr": "D3F1B19781974EB7AF18EE2E5CC58CC7", "action_flag": 3, "change_message": ""}}, {"model": "admin.logentry", "pk": 183, "fields": {"action_time": "2021-12-14T18:22:33.174Z", "user": 5, "content_type": 14, "object_id": "124", "object_repr": "3BC799C4D8B54A6B815C575CB9E23028", "action_flag": 3, "change_message": ""}}, {"model": "admin.logentry", "pk": 184, "fields": {"action_time": "2021-12-14T18:22:33.177Z", "user": 5, "content_type": 14, "object_id": "123", "object_repr": "B8E2D01AA18044DBBDC2759C7B123679", "action_flag": 3, "change_message": ""}}, {"model": "admin.logentry", "pk": 185, "fields": {"action_time": "2021-12-14T18:22:33.181Z", "user": 5, "content_type": 14, "object_id": "122", "object_repr": "EFCA1678394141399FEBA1CF9236F7E5", "action_flag": 3, "change_message": ""}}, {"model": "admin.logentry", "pk": 186, "fields": {"action_time": "2021-12-14T18:22:33.184Z", "user": 5, "content_type": 14, "object_id": "121", "object_repr": "6992E17043A246C9BFEAC04D69D36F5F", "action_flag": 3, "change_message": ""}}, {"model": "admin.logentry", "pk": 187, "fields": {"action_time": "2021-12-14T18:22:33.188Z", "user": 5, "content_type": 14, "object_id": "120", "object_repr": "3997003301844357A11E99741D8DC46E", "action_flag": 3, "change_message": ""}}, {"model": "admin.logentry", "pk": 188, "fields": {"action_time": "2021-12-14T18:22:33.191Z", "user": 5, "content_type": 14, "object_id": "119", "object_repr": "C0D9CAF7E1DA425DBF9EC8F6D1976DB4", "action_flag": 3, "change_message": ""}}, {"model": "admin.logentry", "pk": 189, "fields": {"action_time": "2021-12-14T18:22:33.194Z", "user": 5, "content_type": 14, "object_id": "118", "object_repr": "2C84F1330726485AA74065732A7ED1DF", "action_flag": 3, "change_message": ""}}, {"model": "admin.logentry", "pk": 190, "fields": {"action_time": "2021-12-14T18:22:33.198Z", "user": 5, "content_type": 14, "object_id": "117", "object_repr": "4AA5B6AB8FF0453798D578E4234F38CC", "action_flag": 3, "change_message": ""}}, {"model": "admin.logentry", "pk": 191, "fields": {"action_time": "2021-12-14T18:22:33.201Z", "user": 5, "content_type": 14, "object_id": "116", "object_repr": "8CACA9E559BA4A83B5A7B9075BC419F0", "action_flag": 3, "change_message": ""}}, {"model": "admin.logentry", "pk": 192, "fields": {"action_time": "2021-12-14T18:22:33.205Z", "user": 5, "content_type": 14, "object_id": "115", "object_repr": "92E56CB10E174916879F38495BCAA001", "action_flag": 3, "change_message": ""}}, {"model": "admin.logentry", "pk": 193, "fields": {"action_time": "2021-12-14T18:22:33.208Z", "user": 5, "content_type": 14, "object_id": "114", "object_repr": "3855D4BEFCAE45F28A3D427F7854460B", "action_flag": 3, "change_message": ""}}, {"model": "admin.logentry", "pk": 194, "fields": {"action_time": "2021-12-14T18:22:33.211Z", "user": 5, "content_type": 14, "object_id": "113", "object_repr": "E23F93EAE9F84487A483932521AD3C60", "action_flag": 3, "change_message": ""}}, {"model": "admin.logentry", "pk": 195, "fields": {"action_time": "2021-12-14T18:22:33.214Z", "user": 5, "content_type": 14, "object_id": "112", "object_repr": "93AAA5088C5C4BC7974639726BBCAA70", "action_flag": 3, "change_message": ""}}, {"model": "admin.logentry", "pk": 196, "fields": {"action_time": "2021-12-14T18:22:33.218Z", "user": 5, "content_type": 14, "object_id": "111", "object_repr": "950961692DE6447D9EE828090CB00C96", "action_flag": 3, "change_message": ""}}, {"model": "admin.logentry", "pk": 197, "fields": {"action_time": "2021-12-14T18:22:33.221Z", "user": 5, "content_type": 14, "object_id": "110", "object_repr": "6783E007E76B410CB5F3CBD11294A717", "action_flag": 3, "change_message": ""}}, {"model": "admin.logentry", "pk": 198, "fields": {"action_time": "2021-12-14T18:22:33.225Z", "user": 5, "content_type": 14, "object_id": "109", "object_repr": "68CC46A733FE445D9EF5FE76E4479505", "action_flag": 3, "change_message": ""}}, {"model": "admin.logentry", "pk": 199, "fields": {"action_time": "2021-12-14T18:22:33.228Z", "user": 5, "content_type": 14, "object_id": "108", "object_repr": "C799482E932A4AB498BCA394B95BA019", "action_flag": 3, "change_message": ""}}, {"model": "admin.logentry", "pk": 200, "fields": {"action_time": "2021-12-14T18:23:01.286Z", "user": 5, "content_type": 14, "object_id": "204", "object_repr": "C54E01FF3E0C436F985C2CB1A0D236B3", "action_flag": 3, "change_message": ""}}, {"model": "admin.logentry", "pk": 201, "fields": {"action_time": "2021-12-14T18:23:01.290Z", "user": 5, "content_type": 14, "object_id": "107", "object_repr": "CF5D11D5036B4E4CAEB402037A15B308", "action_flag": 3, "change_message": ""}}, {"model": "admin.logentry", "pk": 202, "fields": {"action_time": "2021-12-14T18:23:01.294Z", "user": 5, "content_type": 14, "object_id": "106", "object_repr": "DB04B0BB368E43349F1D6E83DC68631A", "action_flag": 3, "change_message": ""}}, {"model": "admin.logentry", "pk": 203, "fields": {"action_time": "2021-12-14T18:23:01.297Z", "user": 5, "content_type": 14, "object_id": "105", "object_repr": "450CA773E9B1434FA4D5F3CD0F41269F", "action_flag": 3, "change_message": ""}}, {"model": "admin.logentry", "pk": 204, "fields": {"action_time": "2021-12-14T18:23:01.301Z", "user": 5, "content_type": 14, "object_id": "104", "object_repr": "6234BC00E53848A0A1E726985761FBA8", "action_flag": 3, "change_message": ""}}, {"model": "admin.logentry", "pk": 205, "fields": {"action_time": "2021-12-14T18:23:01.304Z", "user": 5, "content_type": 14, "object_id": "103", "object_repr": "1B7A31ACFAC14C5B96CF2095F7EA0D3F", "action_flag": 3, "change_message": ""}}, {"model": "admin.logentry", "pk": 206, "fields": {"action_time": "2021-12-14T18:23:01.308Z", "user": 5, "content_type": 14, "object_id": "102", "object_repr": "71D87B6C955B448697007D664F159DD6", "action_flag": 3, "change_message": ""}}, {"model": "admin.logentry", "pk": 207, "fields": {"action_time": "2021-12-14T18:23:01.312Z", "user": 5, "content_type": 14, "object_id": "101", "object_repr": "496055787D654CE3A02B3CA2A731565D", "action_flag": 3, "change_message": ""}}, {"model": "admin.logentry", "pk": 208, "fields": {"action_time": "2021-12-14T18:23:01.315Z", "user": 5, "content_type": 14, "object_id": "100", "object_repr": "DA0443D36123422AA111B691CF847FA0", "action_flag": 3, "change_message": ""}}, {"model": "admin.logentry", "pk": 209, "fields": {"action_time": "2021-12-14T18:23:01.319Z", "user": 5, "content_type": 14, "object_id": "99", "object_repr": "74A79EA483544270AF3C4614C7FE8E72", "action_flag": 3, "change_message": ""}}, {"model": "admin.logentry", "pk": 210, "fields": {"action_time": "2021-12-14T18:23:01.322Z", "user": 5, "content_type": 14, "object_id": "98", "object_repr": "05467BB318DA4223BCE2AC22FD60A996", "action_flag": 3, "change_message": ""}}, {"model": "admin.logentry", "pk": 211, "fields": {"action_time": "2021-12-14T18:23:01.326Z", "user": 5, "content_type": 14, "object_id": "97", "object_repr": "7CD0B3A3799E42E3B00D30C9B7E7A0AF", "action_flag": 3, "change_message": ""}}, {"model": "admin.logentry", "pk": 212, "fields": {"action_time": "2021-12-14T18:23:01.329Z", "user": 5, "content_type": 14, "object_id": "96", "object_repr": "7805334E36F640619B475F724521833A", "action_flag": 3, "change_message": ""}}, {"model": "admin.logentry", "pk": 213, "fields": {"action_time": "2021-12-14T18:23:01.332Z", "user": 5, "content_type": 14, "object_id": "95", "object_repr": "792B3CF4CBE34A13A6324ACD8B7DEA3B", "action_flag": 3, "change_message": ""}}, {"model": "admin.logentry", "pk": 214, "fields": {"action_time": "2021-12-14T18:23:01.335Z", "user": 5, "content_type": 14, "object_id": "94", "object_repr": "4F03A906C46D4CFB931852314B6D19AA", "action_flag": 3, "change_message": ""}}, {"model": "admin.logentry", "pk": 215, "fields": {"action_time": "2021-12-14T18:23:01.339Z", "user": 5, "content_type": 14, "object_id": "93", "object_repr": "BC864C5A00B64798966298E75FB51479", "action_flag": 3, "change_message": ""}}, {"model": "admin.logentry", "pk": 216, "fields": {"action_time": "2021-12-14T18:23:01.343Z", "user": 5, "content_type": 14, "object_id": "92", "object_repr": "BD9538DEB2FD4AD3AEC9C9C363C888E1", "action_flag": 3, "change_message": ""}}, {"model": "admin.logentry", "pk": 217, "fields": {"action_time": "2021-12-14T18:23:01.346Z", "user": 5, "content_type": 14, "object_id": "91", "object_repr": "597FFC5A58CC44FABDA8FFAB714D4066", "action_flag": 3, "change_message": ""}}, {"model": "admin.logentry", "pk": 218, "fields": {"action_time": "2021-12-14T18:23:01.350Z", "user": 5, "content_type": 14, "object_id": "90", "object_repr": "32B46629B5EA46CC92F90817E27D8EFF", "action_flag": 3, "change_message": ""}}, {"model": "admin.logentry", "pk": 219, "fields": {"action_time": "2021-12-14T18:23:01.354Z", "user": 5, "content_type": 14, "object_id": "89", "object_repr": "F7F21E04594E42048A30CD9F7DE3B4D8", "action_flag": 3, "change_message": ""}}, {"model": "admin.logentry", "pk": 220, "fields": {"action_time": "2021-12-14T18:23:01.357Z", "user": 5, "content_type": 14, "object_id": "88", "object_repr": "915A8A7BD42D42C9A93FF24BE98AB047", "action_flag": 3, "change_message": ""}}, {"model": "admin.logentry", "pk": 221, "fields": {"action_time": "2021-12-14T18:23:01.361Z", "user": 5, "content_type": 14, "object_id": "87", "object_repr": "1E678966C94849C9ABEB8C731A67E8BB", "action_flag": 3, "change_message": ""}}, {"model": "admin.logentry", "pk": 222, "fields": {"action_time": "2021-12-14T18:23:01.364Z", "user": 5, "content_type": 14, "object_id": "86", "object_repr": "246793A83E244562BA19036963CF329E", "action_flag": 3, "change_message": ""}}, {"model": "admin.logentry", "pk": 223, "fields": {"action_time": "2021-12-14T18:23:01.368Z", "user": 5, "content_type": 14, "object_id": "85", "object_repr": "8E3877852691467B94E657896DC3875E", "action_flag": 3, "change_message": ""}}, {"model": "admin.logentry", "pk": 224, "fields": {"action_time": "2021-12-14T18:23:01.372Z", "user": 5, "content_type": 14, "object_id": "84", "object_repr": "F7A8F537188F46149050EA3E611CE461", "action_flag": 3, "change_message": ""}}, {"model": "admin.logentry", "pk": 225, "fields": {"action_time": "2021-12-14T18:23:01.376Z", "user": 5, "content_type": 14, "object_id": "83", "object_repr": "480AFB59C5F94DB08DF6AEEA1C79DB57", "action_flag": 3, "change_message": ""}}, {"model": "admin.logentry", "pk": 226, "fields": {"action_time": "2021-12-14T18:23:01.380Z", "user": 5, "content_type": 14, "object_id": "82", "object_repr": "D91AC7E147194101BAC7A5F743837534", "action_flag": 3, "change_message": ""}}, {"model": "admin.logentry", "pk": 227, "fields": {"action_time": "2021-12-14T18:23:01.383Z", "user": 5, "content_type": 14, "object_id": "81", "object_repr": "BBABB910411C4D4C98C59294AF64A3C2", "action_flag": 3, "change_message": ""}}, {"model": "admin.logentry", "pk": 228, "fields": {"action_time": "2021-12-14T18:23:01.386Z", "user": 5, "content_type": 14, "object_id": "80", "object_repr": "8A6C1A1205A145AFA88850F3946C850D", "action_flag": 3, "change_message": ""}}, {"model": "admin.logentry", "pk": 229, "fields": {"action_time": "2021-12-14T18:23:01.389Z", "user": 5, "content_type": 14, "object_id": "79", "object_repr": "3F206D2E49CA45FF8BC3E50E6F3C9334", "action_flag": 3, "change_message": ""}}, {"model": "admin.logentry", "pk": 230, "fields": {"action_time": "2021-12-14T18:23:01.391Z", "user": 5, "content_type": 14, "object_id": "78", "object_repr": "10226DA10BDC4F4AA5567FBDB1A6CD2D", "action_flag": 3, "change_message": ""}}, {"model": "admin.logentry", "pk": 231, "fields": {"action_time": "2021-12-14T18:23:01.394Z", "user": 5, "content_type": 14, "object_id": "77", "object_repr": "BA7EAF2550F34C46BE3FBC3A99E505EB", "action_flag": 3, "change_message": ""}}, {"model": "admin.logentry", "pk": 232, "fields": {"action_time": "2021-12-14T18:23:01.398Z", "user": 5, "content_type": 14, "object_id": "76", "object_repr": "FCB2848C563A4F6AA4C3E29B332E3E8E", "action_flag": 3, "change_message": ""}}, {"model": "admin.logentry", "pk": 233, "fields": {"action_time": "2021-12-14T18:23:01.401Z", "user": 5, "content_type": 14, "object_id": "75", "object_repr": "5BD84FFED5FB4B22875EC5FF502FFA00", "action_flag": 3, "change_message": ""}}, {"model": "admin.logentry", "pk": 234, "fields": {"action_time": "2021-12-14T18:23:01.404Z", "user": 5, "content_type": 14, "object_id": "73", "object_repr": "46687E77495F4CD6AA037CAD788D95D3", "action_flag": 3, "change_message": ""}}, {"model": "admin.logentry", "pk": 235, "fields": {"action_time": "2021-12-14T18:23:01.407Z", "user": 5, "content_type": 14, "object_id": "72", "object_repr": "607207EDE6CA47FFB89557946D9F9D4C", "action_flag": 3, "change_message": ""}}, {"model": "admin.logentry", "pk": 236, "fields": {"action_time": "2021-12-14T18:23:01.410Z", "user": 5, "content_type": 14, "object_id": "71", "object_repr": "5A46C9543B234EE7AF19FF4F2EDB8E2B", "action_flag": 3, "change_message": ""}}, {"model": "admin.logentry", "pk": 237, "fields": {"action_time": "2021-12-14T18:23:01.413Z", "user": 5, "content_type": 14, "object_id": "70", "object_repr": "A474471888844B38835FB702E91B691B", "action_flag": 3, "change_message": ""}}, {"model": "admin.logentry", "pk": 238, "fields": {"action_time": "2021-12-14T18:23:01.417Z", "user": 5, "content_type": 14, "object_id": "69", "object_repr": "E562F22BC15D46A9B22B3102FB2BA4BB", "action_flag": 3, "change_message": ""}}, {"model": "admin.logentry", "pk": 239, "fields": {"action_time": "2021-12-14T18:23:01.421Z", "user": 5, "content_type": 14, "object_id": "68", "object_repr": "85D8287986EF41B98D5319BC23EDE741", "action_flag": 3, "change_message": ""}}, {"model": "admin.logentry", "pk": 240, "fields": {"action_time": "2021-12-14T18:23:01.424Z", "user": 5, "content_type": 14, "object_id": "67", "object_repr": "BAC74A0824034CECB9164BBED12B369F", "action_flag": 3, "change_message": ""}}, {"model": "admin.logentry", "pk": 241, "fields": {"action_time": "2021-12-14T18:23:01.428Z", "user": 5, "content_type": 14, "object_id": "66", "object_repr": "D9501D9B54F749A38A09099A218F9F6D", "action_flag": 3, "change_message": ""}}, {"model": "admin.logentry", "pk": 242, "fields": {"action_time": "2021-12-14T18:23:01.431Z", "user": 5, "content_type": 14, "object_id": "65", "object_repr": "608052D5C55D48B0A1CCFB44B43A95C8", "action_flag": 3, "change_message": ""}}, {"model": "admin.logentry", "pk": 243, "fields": {"action_time": "2021-12-14T18:23:01.435Z", "user": 5, "content_type": 14, "object_id": "64", "object_repr": "7995C5A4DD3646539AFE2FC8F924F67C", "action_flag": 3, "change_message": ""}}, {"model": "admin.logentry", "pk": 244, "fields": {"action_time": "2021-12-14T18:23:01.438Z", "user": 5, "content_type": 14, "object_id": "63", "object_repr": "10F8280E51844405A4D22AB4DFCFC885", "action_flag": 3, "change_message": ""}}, {"model": "admin.logentry", "pk": 245, "fields": {"action_time": "2021-12-14T18:23:01.442Z", "user": 5, "content_type": 14, "object_id": "62", "object_repr": "88D2D1A7BEF04CD692B13F193F3C437C", "action_flag": 3, "change_message": ""}}, {"model": "admin.logentry", "pk": 246, "fields": {"action_time": "2021-12-14T18:23:01.445Z", "user": 5, "content_type": 14, "object_id": "61", "object_repr": "60417827232B483387BEFD978CFB9AB8", "action_flag": 3, "change_message": ""}}, {"model": "admin.logentry", "pk": 247, "fields": {"action_time": "2021-12-14T18:23:01.448Z", "user": 5, "content_type": 14, "object_id": "60", "object_repr": "AECD09F4E2C14466AF0059D591665D7E", "action_flag": 3, "change_message": ""}}, {"model": "admin.logentry", "pk": 248, "fields": {"action_time": "2021-12-14T18:23:01.451Z", "user": 5, "content_type": 14, "object_id": "59", "object_repr": "1CB75E4762B14FAA93497F2BB3C1F44C", "action_flag": 3, "change_message": ""}}, {"model": "admin.logentry", "pk": 249, "fields": {"action_time": "2021-12-14T18:23:01.455Z", "user": 5, "content_type": 14, "object_id": "58", "object_repr": "974C2932C2E443D7A558A3F549EC2B4B", "action_flag": 3, "change_message": ""}}, {"model": "admin.logentry", "pk": 250, "fields": {"action_time": "2021-12-14T18:23:01.458Z", "user": 5, "content_type": 14, "object_id": "57", "object_repr": "CC3E64DC3BE44AC2AFF112BFEB5E1865", "action_flag": 3, "change_message": ""}}, {"model": "admin.logentry", "pk": 251, "fields": {"action_time": "2021-12-14T18:23:01.462Z", "user": 5, "content_type": 14, "object_id": "56", "object_repr": "729C2ECA437A461891044FBEAA7FAF51", "action_flag": 3, "change_message": ""}}, {"model": "admin.logentry", "pk": 252, "fields": {"action_time": "2021-12-14T18:23:01.465Z", "user": 5, "content_type": 14, "object_id": "55", "object_repr": "E0AB14DE5DA548E989A85DA9FD819113", "action_flag": 3, "change_message": ""}}, {"model": "admin.logentry", "pk": 253, "fields": {"action_time": "2021-12-14T18:23:01.468Z", "user": 5, "content_type": 14, "object_id": "54", "object_repr": "565B35F9487B4FA4A39E0B6D041BE6F0", "action_flag": 3, "change_message": ""}}, {"model": "admin.logentry", "pk": 254, "fields": {"action_time": "2021-12-14T18:23:01.472Z", "user": 5, "content_type": 14, "object_id": "53", "object_repr": "C9CC411CBBAF4EC18EAAF85A55AD460E", "action_flag": 3, "change_message": ""}}, {"model": "admin.logentry", "pk": 255, "fields": {"action_time": "2021-12-14T18:23:01.475Z", "user": 5, "content_type": 14, "object_id": "52", "object_repr": "56AF97A5747A48C683DAAFBB12A4EDCB", "action_flag": 3, "change_message": ""}}, {"model": "admin.logentry", "pk": 256, "fields": {"action_time": "2021-12-14T18:23:01.479Z", "user": 5, "content_type": 14, "object_id": "51", "object_repr": "4CED226416B5444CA28117AF05D6D13A", "action_flag": 3, "change_message": ""}}, {"model": "admin.logentry", "pk": 257, "fields": {"action_time": "2021-12-14T18:23:01.482Z", "user": 5, "content_type": 14, "object_id": "50", "object_repr": "590D4F1BBBF94BF3B09AD398D494D1F0", "action_flag": 3, "change_message": ""}}, {"model": "admin.logentry", "pk": 258, "fields": {"action_time": "2021-12-14T18:23:01.486Z", "user": 5, "content_type": 14, "object_id": "49", "object_repr": "46F168210EB5460E86C871F246EE4DD8", "action_flag": 3, "change_message": ""}}, {"model": "admin.logentry", "pk": 259, "fields": {"action_time": "2021-12-14T18:23:01.490Z", "user": 5, "content_type": 14, "object_id": "48", "object_repr": "ED4227C93ABA4FA3B18BED8327DFE15B", "action_flag": 3, "change_message": ""}}, {"model": "admin.logentry", "pk": 260, "fields": {"action_time": "2021-12-14T18:23:01.494Z", "user": 5, "content_type": 14, "object_id": "47", "object_repr": "6185A2CA072F47E7BD847522498597E0", "action_flag": 3, "change_message": ""}}, {"model": "admin.logentry", "pk": 261, "fields": {"action_time": "2021-12-14T18:23:01.497Z", "user": 5, "content_type": 14, "object_id": "46", "object_repr": "74A3062692C64725BF5F6DB8B7BA39E2", "action_flag": 3, "change_message": ""}}, {"model": "admin.logentry", "pk": 262, "fields": {"action_time": "2021-12-14T18:23:01.500Z", "user": 5, "content_type": 14, "object_id": "45", "object_repr": "2817774BEC844A1DBC0201FBC4F186D9", "action_flag": 3, "change_message": ""}}, {"model": "admin.logentry", "pk": 263, "fields": {"action_time": "2021-12-14T18:23:01.503Z", "user": 5, "content_type": 14, "object_id": "44", "object_repr": "3F9F3852BFB34B39AB0CB2D99DDA1FF2", "action_flag": 3, "change_message": ""}}, {"model": "admin.logentry", "pk": 264, "fields": {"action_time": "2021-12-14T18:23:01.507Z", "user": 5, "content_type": 14, "object_id": "43", "object_repr": "8D037DEB6A4F417B98765037A564F6B3", "action_flag": 3, "change_message": ""}}, {"model": "admin.logentry", "pk": 265, "fields": {"action_time": "2021-12-14T18:23:01.510Z", "user": 5, "content_type": 14, "object_id": "42", "object_repr": "4AD7B4EB519E4A039A257BF49A60A068", "action_flag": 3, "change_message": ""}}, {"model": "admin.logentry", "pk": 266, "fields": {"action_time": "2021-12-14T18:23:01.514Z", "user": 5, "content_type": 14, "object_id": "41", "object_repr": "FA80A7344C6946BE9A161413A98CF556", "action_flag": 3, "change_message": ""}}, {"model": "admin.logentry", "pk": 267, "fields": {"action_time": "2021-12-14T18:23:01.517Z", "user": 5, "content_type": 14, "object_id": "40", "object_repr": "D564751500D44B13961B2E5959BB0937", "action_flag": 3, "change_message": ""}}, {"model": "auth.user", "pk": 1, "fields": {"password": "pbkdf2_sha256$260000$4dXkxSn8tkGtYSzoHQjBVp$6xXfWqDAw6bmyroc/SO3J3Diw/rvyF5EkNOFS+absLM=", "last_login": "2021-12-14T18:21:39.852Z", "is_superuser": true, "username": "hackettl", "first_name": "", "last_name": "", "email": "lisa-hackett@hotmail.com", "is_staff": true, "is_active": true, "date_joined": "2021-12-01T21:41:12.092Z", "groups": [], "user_permissions": []}}, {"model": "auth.user", "pk": 2, "fields": {"password": "pbkdf2_sha256$260000$x6duNruTdKzRnlEVVuaUeo$Z6kJEJvStLgKIx7mn2Y5CnOE0a5t+d9PWhjv/DP7Ego=", "last_login": null, "is_superuser": true, "username": "lhackett79", "first_name": "", "last_name": "", "email": "lisa-hackett@hotmail.com", "is_staff": true, "is_active": true, "date_joined": "2021-12-05T09:35:18.221Z", "groups": [], "user_permissions": []}}, {"model": "auth.user", "pk": 3, "fields": {"password": "pbkdf2_sha256$260000$dI5XK16UEHlAKUjah2yH6F$gWkX83V8s5bbYRGxaoixuWmyX3dw2u2vKD69Bhpe2Es=", "last_login": "2021-12-05T15:58:33.287Z", "is_superuser": false, "username": "caoilinn", "first_name": "", "last_name": "", "email": "lisa.hackett@ucdconnect.ie", "is_staff": false, "is_active": true, "date_joined": "2021-12-05T15:37:52.107Z", "groups": [], "user_permissions": []}}, {"model": "auth.user", "pk": 5, "fields": {"password": "pbkdf2_sha256$260000$halIqFTtcPXIhpboiDqb71$DpdTpH27tMEFTy/doC9RSPdg+jEdyxLhzFXao0GWlUU=", "last_login": "2021-12-15T20:09:46.431Z", "is_superuser": true, "username": "lhackett", "first_name": "", "last_name": "", "email": "lisa-hackett@hotmail.com", "is_staff": true, "is_active": true, "date_joined": "2021-12-13T07:27:14.631Z", "groups": [], "user_permissions": []}}, {"model": "auth.user", "pk": 6, "fields": {"password": "pbkdf2_sha256$260000$JPCL0TgU9CGx7G5ot6Lt0G$hx+Qbx0+RE04C2FZ21QO0ZsdtC4RDDoMgye1Fy5Pdzg=", "last_login": null, "is_superuser": true, "username": "lisah", "first_name": "", "last_name": "", "email": "lhackett79@gmail.com", "is_staff": true, "is_active": true, "date_joined": "2021-12-13T15:49:46.910Z", "groups": [], "user_permissions": []}}, {"model": "auth.user", "pk": 7, "fields": {"password": "pbkdf2_sha256$260000$WDU6sD5N9xkRPriM9XFkCq$m2qUcN8uAKnrRATF/3nAyjmWLuW8ojjUuHkPI1lbZtY=", "last_login": "2021-12-14T16:58:16.329Z", "is_superuser": false, "username": "jumper", "first_name": "", "last_name": "", "email": "test@test.ie", "is_staff": false, "is_active": true, "date_joined": "2021-12-14T16:57:00.090Z", "groups": [], "user_permissions": []}}, {"model": "sessions.session", "pk": "37becxkk71fsdlk607g9jqb344kfh9h1", "fields": {"session_data": ".eJxVjMsOgyAURP_lrg0BtIAsu-83EB7XSmugAU3aGP-9mrhok1nNnDkrGLvMo1kqFhMDaGDQ_HbO-iemYwgPm-6Z-JzmEh05EHKuldxywOl6sn-C0dZxfyMVzElBUXrHFUclh44jC2GP9P0wYEfbixBKBtFy3wdFPWPMSiU87xke0oq1xpwMvl-xfEDTBrwtM-gVWtBpmaZt-wIk5USj:1mtzDa:MrpAzraC0zEq0-RMxOe2f0349i3oVoUPzDUJR9eHJ5k", "expire_date": "2021-12-19T21:38:46.175Z"}}, {"model": "sessions.session", "pk": "4alt0gfdb02ltaf1f6l7ybcny8bteimv", "fields": {"session_data": ".eJxVjMEOwiAQRP-FsyEsXQp69O43kIUFqRpISnsy_rtt0oMeZ96beQtP61L82tPsJxYXAeL02wWKz1R3wA-q9yZjq8s8Bbkr8qBd3hqn1_Vw_w4K9bKtwwguRURwwcUwqEBIGTRnRUYjaQc2GlQI0drRUuIzM6kBKWXYghGfL-pnOEk:1mtUOB:7dP6ud6_BOZ4xAYyA7F2EiumpunJehC6oVOyfawLOdc", "expire_date": "2021-12-18T12:43:39.819Z"}}, {"model": "sessions.session", "pk": "6k9rs68uf9i098dtbdu5pq8ndneez4cn", "fields": {"session_data": ".eJxVjEEOgyAURO_C2hBQFOqy-56BfPjfStuAAU3aGO9eTVy0y5l581ZmYZlHuxTKNiDrmWTVb-fAPykeAz4g3hP3Kc45OH4g_FwLvyWk1_Vk_wQjlHF_u04a8kpJ44x3jXCgYJA1DgLaWkFtpPatEkp6rTsNhBdEEI0CGuQe2kNaqJSQoqX3FPKH9aJiHvLM-nXbviSGQtI:1msmNK:DUXn7r9oR1MrPcLnz3ntanMeQa5Tu4rmcWNOOMo-IpI", "expire_date": "2021-12-16T13:43:50.594Z"}}, {"model": "sessions.session", "pk": "7m0ffw2g7jxs0pmvk3ncyj7apacxwjz2", "fields": {"session_data": ".eJxVjMsOwiAURP_lrhsCtALt0r3fQHhcLGrAADUa47_bJl1oMquZM-cN2ixt1kvFoqOHCRh0v5017oppG_zFpHMmLqdWoiUbQva1klP2eDvu7J9gNnVe30gFs1JQlM5yxVHJMHBk3q-RbgwBB9ofhFDSi5670SvqGGNGKuH4yHCTVqw15qTxeY_lBRPtoJoH6phChqmVBT9f6WpFDw:1musn2:mRaKkvfslSj0nqh4gu3-sNzXpADhxLcs7Pg-eSvpPE4", "expire_date": "2021-12-22T08:59:04.054Z"}}, {"model": "sessions.session", "pk": "7qa63mu2ijlrvrvoiu6vu4pfpwxlcdf8", "fields": {"session_data": ".eJxVjMEOwiAQRP-FsyEsXQp69O43kIUFqRpISnsy_rtt0oMeZ96beQtP61L82tPsJxYXAeL02wWKz1R3wA-q9yZjq8s8Bbkr8qBd3hqn1_Vw_w4K9bKtwwguRURwwcUwqEBIGTRnRUYjaQc2GlQI0drRUuIzM6kBKWXYghGfL-pnOEk:1msXME:o-cMqiLo40BbT3HODsckZkmrgIe7KRn2qg747293Uq4", "expire_date": "2021-12-15T21:41:42.925Z"}}, {"model": "sessions.session", "pk": "8nu28c4do5b291nadlho7x40zyv6iw1l", "fields": {"session_data": ".eJxVjMsOgjAQRf9l1oSUR6V06d5vaKadQaqkNS0YDeHflYSFbu8596xgcJlHs2ROxhNokFD8bhbdncMO6IbhGksXw5y8LXelPGguL5F4Oh_uX2DEPH7fSopGqp7IkWqVlcJxjbJqiSWrvqu6tu4JT9xb1YnGWjkMriFLqsOmFmrYo5lz9jEYfj18eoMWBWR8svFhiKDntHABDtMMeoUWdFimads-BypLNw:1mxbhQ:DbqePo_TkmBBiq9Pt3TeUoT76OQZHfZLZAZhf2mDxSE", "expire_date": "2021-12-29T21:20:32.632Z"}}, {"model": "sessions.session", "pk": "cmh3i2chzgehxcngrh6q451gl5d01f8w", "fields": {"session_data": ".eJxVjEsOgzAMBe_idRUFghuHZfc9A3JiU2hRkPisEHcvSCza7Zt5s0HD69I166xT0wvUgHD73SKnj-YTyJvzazRpzMvUR3Mq5qKzeY6iw-Ny_wIdz93xJrQOKYgkoYoi2qQlY1GJolLwha_KIHzXEMlbFyO2bXIShTy70lJ7RBNPC9QbFFDndRj2_QsCDT3T:1mxQGA:XiBUipuECSXVz3lfPMkMxId10Dv1mNeQFgRNNl0AMD8", "expire_date": "2021-12-29T09:07:38.647Z"}}, {"model": "sessions.session", "pk": "dzi5xweehqp6csx5nmyw79f2rid0y9ex", "fields": {"session_data": ".eJxVTksOwiAUvMtbNwRoBcrSvWcgfF4t2oCBNtE0vbttdKHJLCbzy6xg7DKPZqlYTAyggUHzqznr75gOI9xsumbic5pLdOSIkK9bySUHnM7f7N_AaOu4t5EK5qSgKL3jiqOSQ8eRhbBD-n4YsKPtSQglg2i574OinjFmpRKe9wyP0Yq1xpwMPh-xvEDTBrwtM-h1f63TMk0NtB-ybW-VSkc5:1muVdK:Oi6K7sn5HQPGW7GzP4k_FKWM6eWNF2FsuWEpZZJnGtQ", "expire_date": "2021-12-21T08:15:30.733Z"}}, {"model": "sessions.session", "pk": "iyip4t44l5830zzky8vuhqjuzin23yi2", "fields": {"session_data": "e30:1mwfkc:QDrBxmCmKVF3fO2nye9sD0MkPj27JnMYRY6cxsfBBbc", "expire_date": "2021-12-27T07:27:58.818Z"}}, {"model": "sessions.session", "pk": "jun2q2fqouazry4pqy3w6koh0djtjr8m", "fields": {"session_data": ".eJxVjMsOwiAURP_lrhsCtALt0r3fQHhcLGrAADUa47_bJl1oMquZM-cN2ixt1kvFoqOHCRh0v5017oppG_zFpHMmLqdWoiUbQva1klP2eDvu7J9gNnVe30gFs1JQlM5yxVHJMHBk3q-RbgwBB9ofhFDSi5670SvqGGNGKuH4yHCTVqw15qTxeY_lBRPtoJoH6phChqmVBT9f6WpFDw:1mvRLS:j37NloRmUMNb8h3txmwQY2Bm6kyTQFiEPl0P91yHAM8", "expire_date": "2021-12-23T21:52:54.937Z"}}, {"model": "sessions.session", "pk": "k28v7bgwi7alxr7vzi8dbeu4gfl4o73i", "fields": {"session_data": ".eJxVTksOgyAQvcusDQFFoS677xnIAGOlbaARTdoY715JXbSzeZn3y1vB4DKPZsk0meChBwHVL2fR3SkWwd8wXhNzKc5TsKxY2KFmdkmeHufD-1cwYh73tO2EJiel0FY723CLEgdR-4FjW0ustVCulVwKp1SnkPzJe-SNRBrE_rSlNFPOIUVDr2eY3tDzChxOM_Trvvq7vCn4Pdi2D7mQRm4:1mssJR:6sftzxecDtpxc1gxi08gyJ-XZWnv66Y6zKbjftX4EME", "expire_date": "2021-12-16T20:04:13.162Z"}}, {"model": "sessions.session", "pk": "k2hvj9ajhecsj465si2e1kwmg5rqclj7", "fields": {"session_data": ".eJxVTksOwiAUvMtbNwRoBcrSvWcgfF4t2oCBNtE03t02dqHJLCbzy6xg7DKPZqlYTAyggUHzqznr75h2I9xsumbic5pLdGSPkMOt5JIDTucj-zcw2jpubaSCOSkoSu-44qjk0HFkIWyQvh8G7Gh7EkLJIFru-6CoZ4xZqYTnPcN9tGKtMSeDz0csL9C0AW_LDHqFFnRapqnZ7h-k-5L3-wMdQ0nS:1muhlk:z68FhVoQP0RrVVAF0stFn1E5ZODG7ZGI8XPjOj2Idu8", "expire_date": "2021-12-21T21:13:00.904Z"}}, {"model": "sessions.session", "pk": "lkajcrzx8r9461vzl48ctblge5cxrkth", "fields": {"session_data": ".eJxVjMEOwiAQRP-FsyEsrUB79O43ENjdWtSAKW2iMf67bdKDJnOaefPewodlHv1SefKJRC9AHH67GPDGeRvoGvKlSCx5nlKUGyL3tcpzIb6fdvZPMIY6rm9WBqI1ii1G7TQ7O7SagWiNxW4YuFXN0RhnyTQaO3IKASBYZ1B3wJu0cq2pZM_PR5peolefL4lCPus:1mu8OH:eSqfX6xDp5E0iZ96JzsfH1hddwByBHIsJ2QauNKdvYI", "expire_date": "2021-12-20T07:26:25.745Z"}}, {"model": "sessions.session", "pk": "lse646dorxvl7wqk8r8pmjjaodp3crxd", "fields": {"session_data": ".eJxVjMsOgjAQRf9l1oSUR6V06d5vaKadQaqkNS0YDeHflYSFbu8596xgcJlHs2ROxhNokFD8bhbdncMO6IbhGksXw5y8LXelPGguL5F4Oh_uX2DEPH7fSopGqp7IkWqVlcJxjbJqiSWrvqu6tu4JT9xb1YnGWjkMriFLqsOmFmrYo5lz9jEYfj18eoMWBWR8svFhiKDntHABDtMMeoUWdFimads-BypLNw:1mwhIg:SyLTKUwEoZYxE6R0AIsygO1mrhvoGflD-OqyX86fQEs", "expire_date": "2021-12-27T09:07:14.215Z"}}, {"model": "sessions.session", "pk": "m32bo2iudgnj9w9sogfgnwlleelht27k", "fields": {"session_data": "eyJhY2NvdW50X3ZlcmlmaWVkX2VtYWlsIjpudWxsLCJhY2NvdW50X3VzZXIiOiI0In0:1mwffc:R9uGAY_5N-E0SjsHPAU7FRde0zgp6QPZaxcdZAxuJVM", "expire_date": "2021-12-27T07:22:48.452Z"}}, {"model": "sessions.session", "pk": "oqgf14no5b2yixd12k3qdkr0cdptm576", "fields": {"session_data": "e30:1mwfhN:lazu8CJzjg56yxU5jWE-NQcnzsOJ9unhVZxiBxILIiQ", "expire_date": "2021-12-27T07:24:37.575Z"}}, {"model": "sessions.session", "pk": "p6pc8tua3yfkker2ec0dj3iurcukhgn9", "fields": {"session_data": "e30:1mwfgG:OrtXgIsoJZe358l-vql6Ha7cRGdugLyqJGG7E9__wiM", "expire_date": "2021-12-27T07:23:28.980Z"}}, {"model": "sessions.session", "pk": "q3mz05jkqx16e2sr1ew57z4te68kbv5f", "fields": {"session_data": ".eJxVjMsOgyAURP_lrg0BtIAsu-83EB7XSmugAU3aGP-9mrhok1nNnDkrGLvMo1kqFhMDaGDQ_HbO-iemYwgPm-6Z-JzmEh05EHKuldxywOl6sn-C0dZxfyMVzElBUXrHFUclh44jC2GP9P0wYEfbixBKBtFy3wdFPWPMSiU87xke0oq1xpwMvl-xfEDTBrwtM-gVOOi0TNO2fQEk3ESi:1muLG5:v9lFqi0LP-_CXR40DIkKfeZN134ivwe_s634KEsCqKA", "expire_date": "2021-12-20T21:10:49.917Z"}}, {"model": "sessions.session", "pk": "st8cb61n9ckpmhusvbekb9viing9v6qw", "fields": {"session_data": ".eJxVjMsOwiAURP_lrhsCtALt0r3fQHhcLGrAADUa47_bJl1oMquZM-cN2ixt1kvFoqOHCRh0v5017oppG_zFpHMmLqdWoiUbQva1klP2eDvu7J9gNnVe30gFs1JQlM5yxVHJMHBk3q-RbgwBB9ofhFDSi5670SvqGGNGKuH4yHCTVqw15qTxeY_lBRPtoJoH6phChqmVBT9f6WpFDw:1mvMQg:nnxZRTRqrweD8CBm9PwHRdy6cxn80NBpm_l7xuVWAs4", "expire_date": "2021-12-23T16:37:58.397Z"}}, {"model": "sessions.session", "pk": "te2j7ezc7p4oou195n4qool3j0ntuqgp", "fields": {"session_data": ".eJxVjMsOwiAURP_lrhsCtALt0r3fQHhcLGrAADUa47_bJl1oMquZM-cN2ixt1kvFoqOHCRh0v5017oppG_zFpHMmLqdWoiUbQva1klP2eDvu7J9gNnVe30gFs1JQlM5yxVHJMHBk3q-RbgwBB9ofhFDSi5670SvqGGNGKuH4yHCTVqw15qTxeY_lBRPtoJoH6phChqmVBT9f6WpFDw:1mvygR:8Up2A3YxtO-gXVIYGNAJbbJJcKdxEXkS7rqkiIZfrxY", "expire_date": "2021-12-25T09:28:47.445Z"}}, {"model": "sessions.session", "pk": "x63ewwus2g6yf002oepnxslmdq42q4c5", "fields": {"session_data": ".eJxVjksOgjAQhu8ya9K00NLapXvP0EwfSJUU00KiIdxdiJjo7pv_lVnA4Dz1Zi4hm-hBA4PqV7Po7iHthr9huo7EjWnK0ZI9Qg63kMvow3A-sn8DPZZ-a9uWqeA4Z8oqZxtqkWPHat9RFDXHWjHpBKecOSlbicGfvEfacAwd2w6xj5ZQShyTCc9HzC_QtAKHeQK9QAM6zcNQbe8fIL7AP7Cub-j8TQc:1mtF8U:CUSt4fniS-GXFr_Xx5DjTomzA_yieUA9orr0GGGiv5M", "expire_date": "2021-12-17T20:26:26.972Z"}}, {"model": "sessions.session", "pk": "zuixvr1t5970gmj8i5a0db4o5tvm9a55", "fields": {"session_data": ".eJxVjMsOwiAQRf9l1k1DHwhl6d5vIAMztWgDBlqjMf67NulCt_ece15gcV0muxbONhAYkFD9bg79leMG6ILxnGqf4pKDqzel3mmpT4l4Pu7uX2DCMn3fWopO6oHIk-61k8Jzi7LpiSXrQTWqbwfCAw9OK9E5J8fRd-RIK-xaocctWriUkKLlxy3kJxhRQcE72xDHBGbJK1fgMS9gXqDAxHWe3-8PB0VLOg:1mwvRs:6pr-HfKASBFJsVOj7qXr5kNMDVC6H0ET9uXqQyBJ99U", "expire_date": "2021-12-28T00:13:40.707Z"}}, {"model": "sites.site", "pk": 1, "fields": {"domain": "Help_My_Plants", "name": "helpmyplants.com"}}, {"model": "account.emailaddress", "pk": 2, "fields": {"user": 3, "email": "lisa.hackett@ucdconnect.ie", "verified": true, "primary": true}}, {"model": "account.emailaddress", "pk": 4, "fields": {"user": 5, "email": "lisa-hackett@hotmail.com", "verified": true, "primary": true}}, {"model": "account.emailaddress", "pk": 5, "fields": {"user": 7, "email": "test@test.ie", "verified": false, "primary": true}}, {"model": "account.emailaddress", "pk": 6, "fields": {"user": 7, "email": "test@test.com", "verified": true, "primary": true}}, {"model": "services.service", "pk": 1, "fields": {"name": "New Consultation", "description": "This is an appointment for a new consultation, where we can discuss your needs, and give you some advice and direction", "price": "55.00", "image": "card-hanging-plant.jpg"}}, {"model": "services.service", "pk": 2, "fields": {"name": "Follow up Consultation- Plant Care", "description": "This is an opportunity for you to discuss what you had learnt from the initial appointment and let us answer all your queries. 60 minute slots.", "price": "50.00", "image": "aloe-vera-2.jpg"}}, {"model": "services.service", "pk": 3, "fields": {"name": "Help  my plants", "description": "A shopping expidition", "price": "45.00", "image": "green-plant.jpg"}}, {"model": "services.service", "pk": 4, "fields": {"name": "test", "description": "test", "price": "45.00", "image": "Cactus1.jpg"}}, {"model": "services.service", "pk": 7, "fields": {"name": "Health Benefits of Indoor Plants", "description": "A 30 minute online session, where you can learn about the Health Benefits to keeping healthy plants in your indoor space.", "price": "20.00", "image": "green-plant_1fHVcvx.jpg"}}, {"model": "checkout.order", "pk": 205, "fields": {"order_number": "9EC6B7088DC54B13906401DE16F37593", "user_profile": 2, "customer_name": "New Monday WH Test", "email": "Lisa-hackett@hotmail.com", "phone_number": "12121212112121212", "order_total": "45.00", "date": "2021-12-13", "original_cart": "", "stripe_pid": ""}}, {"model": "checkout.order", "pk": 206, "fields": {"order_number": "CBFADD3E8C3E41B380434A7EB362EFE5", "user_profile": 2, "customer_name": "New testing DAte", "email": "Lisa-hackett@hotmail.com", "phone_number": "0123456789", "order_total": "150.00", "date": "2021-12-13", "original_cart": "", "stripe_pid": ""}}, {"model": "checkout.order", "pk": 207, "fields": {"order_number": "3004B790C0D6484B9F860F95CC11D517", "user_profile": 2, "customer_name": "DAte Check", "email": "Lisa-hackett@hotmail.com", "phone_number": "0123456789", "order_total": "45.00", "date": "2021-12-13", "original_cart": "", "stripe_pid": ""}}, {"model": "checkout.order", "pk": 208, "fields": {"order_number": "6951BC2A330447AEA089BF4C4E0E7D38", "user_profile": 2, "customer_name": "User WH Test", "email": "Lisa-hackett@hotmail.com", "phone_number": "0123456789", "order_total": "60.00", "date": "2021-12-13", "original_cart": "", "stripe_pid": ""}}, {"model": "checkout.order", "pk": 209, "fields": {"order_number": "EE7F920CA29B42E5A9D388D15AA05C2C", "user_profile": 4, "customer_name": "JumperOne", "email": "test@test.ie", "phone_number": "321321", "order_total": "55.00", "date": "2021-12-14", "original_cart": "", "stripe_pid": ""}}, {"model": "checkout.order", "pk": 210, "fields": {"order_number": "DFA89B2C8EF044349E7F427636FC2C46", "user_profile": 2, "customer_name": "new test", "email": "Lisa-hackett@hotmail.com", "phone_number": "0123456789", "order_total": "55.00", "date": "2021-12-15", "original_cart": "", "stripe_pid": ""}}, {"model": "checkout.orderitem", "pk": 221, "fields": {"order": 205, "service": 3, "date_picked": null, "item_total": "45.00"}}, {"model": "checkout.orderitem", "pk": 222, "fields": {"order": 206, "service": 2, "date_picked": "2021-12-14", "item_total": "60.00"}}, {"model": "checkout.orderitem", "pk": 223, "fields": {"order": 206, "service": 1, "date_picked": "2021-12-22", "item_total": "55.00"}}, {"model": "checkout.orderitem", "pk": 225, "fields": {"order": 207, "service": 3, "date_picked": null, "item_total": "45.00"}}, {"model": "checkout.orderitem", "pk": 226, "fields": {"order": 208, "service": 2, "date_picked": null, "item_total": "60.00"}}, {"model": "checkout.orderitem", "pk": 227, "fields": {"order": 209, "service": 1, "date_picked": null, "item_total": "55.00"}}, {"model": "checkout.orderitem", "pk": 228, "fields": {"order": 210, "service": 1, "date_picked": null, "item_total": "55.00"}}, {"model": "articles.article", "pk": 1, "fields": {"title": "Test Article", "content": "The Force is strong with this one. I have you now. A tremor in the Force. The last time I felt it was in the presence of my old master. She must have hidden the plans in the escape pod. Send a detachment down to retrieve them, and see to it personally, Commander. There'll be no one to stop us this time!\r\n\r\nShe must have hidden the plans in the escape pod. Send a detachment down to retrieve them, and see to it personally, Commander. There'll be no one to stop us this time! I need your help, Luke. She needs your help. I'm getting too old for this sort of thing.\r\n\r\nYou don't believe in the Force, do you? Alderaan? I'm not going to Alderaan. I've got to go home. It's late, I'm in for it as it is. I'm trying not to, kid. You are a part of the Rebel Alliance and a traitor! Take her away!", "image": "bonsai-1.jpg", "created_date": "2021-12-04"}}, {"model": "articles.article", "pk": 2, "fields": {"title": "Health Benefits of Plants", "content": "1. Indoor plants may help reduce stress levels\r\nA studyTrusted Source published in the Journal of Physiological Anthropology found that plants in your home or office can make you feel more comfortable, soothed, and natural.\r\nResearchers concluded that working with plants could reduce both physiological and psychological stress.\r\n\r\n\r\n2. Real plants may sharpen your attention\r\nSorry, plastic plants wont help you pass your exams. In a small study involving 23 participants, researchers put students in a classroom with either a fake plant, a real one, a photograph of a plant, or no plant at all.\r\n\r\nBrain scans of the participants showed that the students who studied with real, live plants in the classroom were more attentive and better able to concentrate than students in the other groups.\r\n\r\n3. Working with plants can be therapeutic\r\nFor people experiencing the symptoms of mental illness, indoor gardening can be helpful.\r\n\r\nResearchersTrusted Source have used horticultural therapy to increase feelings of well-being among people with depression, anxiety, dementia, and other conditions.\r\n\r\nAlthough horticultural therapy has been around for centuries, it has found a modern expression: Medical clinics in Manchester, England are now prescribing potted plants to patients with depression or anxiety symptoms\r\n\r\n4. Plants may help you recover from illness faster\r\nBeing able to look at plants and flowers may speed your recovery from an illness, injury, or surgery.\r\n\r\nA 2002 review of the research revealed that people recuperating from several kinds of surgery needed less pain medication and had shorter hospital stays than people who werent looking at greenery during their recovery periods.\r\n\r\nIts important to note that most research focuses on plants and natural scenery in hospital settings rather than at home.\r\n\r\n5. Plants may boost your productivity\r\nA bromeliad may turn out to be the best cubicle-mate youve ever had.\r\n\r\nMultiple studies have found that plants in the workspace increase both productivity and creativity. One frequently cited study from 1996 found that students in a campus computer lab worked 12 percent faster and were less stressed when plants were placed nearby.\r\n\r\nIn a 2004 studyTrusted Source, researchers challenged people to make creative word associations. They performed better when a plant was in the room with them.\r\n\r\nAnd a 2007 study showed that people with more plants in their workspace took fewer sick days and were more productive on the job.\r\n\r\n6. Plants may improve your whole outlook on work\r\nA view of the city park might improve anyones job satisfaction  but it might surprise you to learn that a potted plant could have a similar effect.\r\n\r\nResearchersTrusted Source interviewed over 440 Amazon employees in India and the United States. They found that those whose office environment included natural elements like indoor plants felt greater job satisfaction and more commitment to the organization than those who didnt work around natural elements.\r\n\r\nResearchers said the natural elements helped to buffer the effects of job stress and anxiety.\r\n\r\n7. Plants may improve the quality of indoor air\r\nScientific support for phytoremediation  thats the word for plants scrubbing contaminants from the air  usually begins with a NASA study conducted in the 1980s.\r\n\r\nResearchers then were looking for ways to improve the air quality in a sealed spacecraft, and they concluded that the roots and soil of houseplants reduced airborne volatile organic compounds (VOCs) significantly.\r\n\r\nSince those early studies, researchers have both confirmed those findings and called them into questionTrusted Source.\r\n\r\nRecent findings suggest that youd have to shelter a large number of plants to equal the air purifying efficiency of modern biofilters and other technologies", "image": "pink-orchid.jpg", "created_date": "2021-12-05"}}, {"model": "profiles.userprofile", "pk": 2, "fields": {"user": 5, "default_phone_number": "0123456789", "default_email": "Lisa-hackett@hotmail.com"}}, {"model": "profiles.userprofile", "pk": 3, "fields": {"user": 6, "default_phone_number": null, "default_email": null}}, {"model": "profiles.userprofile", "pk": 4, "fields": {"user": 7, "default_phone_number": "321321", "default_email": "test@test.ie"}}]